Workbook

Sheet Accueil
A1: MG HÔTE — TABLEAU DE BORD
A2: Conciergerie · Airbnb / Booking / Location courte durée · Villas, Appartements, Riads
G3: Date du jour : | H3: =TODAY() -> 46224
A4: AUJOURD'HUI & CE MOIS-CI
A5: Arrivées aujourd'hui | B5: Départs aujourd'hui | C5: Arrivées 7 prochains jours | D5: Ménages en attente | E5: Nuits réservées (mois)
A6: =COUNTIFS(Réservations!$F$4:$F$303,TODAY(),Réservations!$P$4:$P$303,"<>Annulée") -> 1 | B6: =COUNTIFS(Réservations!$G$4:$G$303,TODAY(),Réservations!$P$4:$P$303,"<>Annulée") -> 0 | C6: =COUNTIFS(Réservations!$F$4:$F$303,">="&TODAY(),Réservations!$F$4:$F$303,"<="&TODAY()+7,Réservations!$P$4:$P$303,"<>Annulée") -> 1 | D6: =COUNTIF(Ménage!$D$4:$D$203,"En attente") -> 1 | E6: =SUMIFS(Réservations!$H$4:$H$303,Réservations!$T$4:$T$303,MONTH(TODAY()),Réservations!$U$4:$U$303,YEAR(TODAY()),Réservations!$P$4:$P$303,"<>Annulée") -> 8
A8: BLOC FINANCIER (mois en cours)
A9: Taux occupation (mois) | B9: CA brut (mois) | C9: Revenus MG Hôte (mois) | D9: Dépenses (mois) | E9: Résultat MG Hôte (mois)
A10: =IF(Paramètres!$B$20=0,0,E6/(DAY(EOMONTH(TODAY(),0))*Paramètres!$B$20)) -> 0.25806452 | B10: =SUMIFS(Réservations!$J$4:$J$303,Réservations!$T$4:$T$303,MONTH(TODAY()),Réservations!$U$4:$U$303,YEAR(TODAY()),Réservations!$P$4:$P$303,"<>Annulée") -> 5400 | C10: =SUMIFS(Réservations!$N$4:$N$303,Réservations!$T$4:$T$303,MONTH(TODAY()),Réservations!$U$4:$U$303,YEAR(TODAY()),Réservations!$P$4:$P$303,"<>Annulée") -> 980.4 | D10: =SUMIFS(Dépenses!$E$4:$E$303,Dépenses!$F$4:$F$303,MONTH(TODAY()),Dépenses!$G$4:$G$303,YEAR(TODAY())) -> 530 | E10: =C10-D10 -> 450.4
A12: ALERTES
A13: Paiements en retard | C13: =COUNTIFS(Réservations!$Q$4:$Q$303,"Non",Réservations!$G$4:$G$303,"<"&TODAY(),Réservations!$P$4:$P$303,"<>Annulée") -> 0 | D13: =IF(C13>0,"⚠ À traiter","✓ OK") -> ✓ OK
A14: Ménages oubliés (date passée) | C14: =COUNTIFS(Ménage!$D$4:$D$203,"En attente",Ménage!$A$4:$A$203,"<"&TODAY()) -> 0 | D14: =IF(C14>0,"⚠ À traiter","✓ OK") -> ✓ OK
A15: Rentabilité faible ce mois-ci | C15: =IF(E10<Paramètres!$B$24,1,0) -> 1 | D15: =IF(C15>0,"⚠ À traiter","✓ OK") -> ⚠ À traiter
A16: Logements vides trop longtemps | C16: =COUNTIF($E$19:$E$28,"À relancer") -> 0 | D16: =IF(C16>0,"⚠ À traiter","✓ OK") -> ✓ OK
A17: SUIVI PAR BIEN
A18: Bien | B18: Actif | C18: Dernier départ | D18: Jours vides | E18: Alerte
A19: =Paramètres!A9 -> Bien 1 | B19: =Paramètres!B9 -> Oui | C19: =IF(B19<>"Oui","",IF(_xlfn.MAXIFS(Réservations!$G$4:$G$303,Réservations!$B$4:$B$303,A19)=0,"",_xlfn.MAXIFS(Réservations!$G$4:$G$303,Réservations!$B$4:$B$303,A19))) -> 46228 | D19: =IF(OR(B19<>"Oui",C19=""),"",MAX(0,TODAY()-C19)) -> 0 | E19: =IF(OR(B19<>"Oui",D19=""),"",IF(D19>Paramètres!$B$23,"À relancer","OK")) -> OK
A20: =Paramètres!A10 -> Bien 2 | B20: =Paramètres!B10 -> Non | C20: =IF(B20<>"Oui","",IF(_xlfn.MAXIFS(Réservations!$G$4:$G$303,Réservations!$B$4:$B$303,A20)=0,"",_xlfn.MAXIFS(Réservations!$G$4:$G$303,Réservations!$B$4:$B$303,A20))) | D20: =IF(OR(B20<>"Oui",C20=""),"",MAX(0,TODAY()-C20)) | E20: =IF(OR(B20<>"Oui",D20=""),"",IF(D20>Paramètres!$B$23,"À relancer","OK"))
A21: =Paramètres!A11 -> Bien 3 | B21: =Paramètres!B11 -> Non | C21: =IF(B21<>"Oui","",IF(_xlfn.MAXIFS(Réservations!$G$4:$G$303,Réservations!$B$4:$B$303,A21)=0,"",_xlfn.MAXIFS(Réservations!$G$4:$G$303,Réservations!$B$4:$B$303,A21))) | D21: =IF(OR(B21<>"Oui",C21=""),"",MAX(0,TODAY()-C21)) | E21: =IF(OR(B21<>"Oui",D21=""),"",IF(D21>Paramètres!$B$23,"À relancer","OK"))
A22: =Paramètres!A12 -> Bien 4 | B22: =Paramètres!B12 -> Non | C22: =IF(B22<>"Oui","",IF(_xlfn.MAXIFS(Réservations!$G$4:$G$303,Réservations!$B$4:$B$303,A22)=0,"",_xlfn.MAXIFS(Réservations!$G$4:$G$303,Réservations!$B$4:$B$303,A22))) | D22: =IF(OR(B22<>"Oui",C22=""),"",MAX(0,TODAY()-C22)) | E22: =IF(OR(B22<>"Oui",D22=""),"",IF(D22>Paramètres!$B$23,"À relancer","OK"))
A23: =Paramètres!A13 -> Bien 5 | B23: =Paramètres!B13 -> Non | C23: =IF(B23<>"Oui","",IF(_xlfn.MAXIFS(Réservations!$G$4:$G$303,Réservations!$B$4:$B$303,A23)=0,"",_xlfn.MAXIFS(Réservations!$G$4:$G$303,Réservations!$B$4:$B$303,A23))) | D23: =IF(OR(B23<>"Oui",C23=""),"",MAX(0,TODAY()-C23)) | E23: =IF(OR(B23<>"Oui",D23=""),"",IF(D23>Paramètres!$B$23,"À relancer","OK"))
A24: =Paramètres!A14 -> Bien 6 | B24: =Paramètres!B14 -> Non | C24: =IF(B24<>"Oui","",IF(_xlfn.MAXIFS(Réservations!$G$4:$G$303,Réservations!$B$4:$B$303,A24)=0,"",_xlfn.MAXIFS(Réservations!$G$4:$G$303,Réservations!$B$4:$B$303,A24))) | D24: =IF(OR(B24<>"Oui",C24=""),"",MAX(0,TODAY()-C24)) | E24: =IF(OR(B24<>"Oui",D24=""),"",IF(D24>Paramètres!$B$23,"À relancer","OK"))
A25: =Paramètres!A15 -> Bien 7 | B25: =Paramètres!B15 -> Non | C25: =IF(B25<>"Oui","",IF(_xlfn.MAXIFS(Réservations!$G$4:$G$303,Réservations!$B$4:$B$303,A25)=0,"",_xlfn.MAXIFS(Réservations!$G$4:$G$303,Réservations!$B$4:$B$303,A25))) | D25: =IF(OR(B25<>"Oui",C25=""),"",MAX(0,TODAY()-C25)) | E25: =IF(OR(B25<>"Oui",D25=""),"",IF(D25>Paramètres!$B$23,"À relancer","OK"))
A26: =Paramètres!A16 -> Bien 8 | B26: =Paramètres!B16 -> Non | C26: =IF(B26<>"Oui","",IF(_xlfn.MAXIFS(Réservations!$G$4:$G$303,Réservations!$B$4:$B$303,A26)=0,"",_xlfn.MAXIFS(Réservations!$G$4:$G$303,Réservations!$B$4:$B$303,A26))) | D26: =IF(OR(B26<>"Oui",C26=""),"",MAX(0,TODAY()-C26)) | E26: =IF(OR(B26<>"Oui",D26=""),"",IF(D26>Paramètres!$B$23,"À relancer","OK"))
A27: =Paramètres!A17 -> Bien 9 | B27: =Paramètres!B17 -> Non | C27: =IF(B27<>"Oui","",IF(_xlfn.MAXIFS(Réservations!$G$4:$G$303,Réservations!$B$4:$B$303,A27)=0,"",_xlfn.MAXIFS(Réservations!$G$4:$G$303,Réservations!$B$4:$B$303,A27))) | D27: =IF(OR(B27<>"Oui",C27=""),"",MAX(0,TODAY()-C27)) | E27: =IF(OR(B27<>"Oui",D27=""),"",IF(D27>Paramètres!$B$23,"À relancer","OK"))
A28: =Paramètres!A18 -> Bien 10 | B28: =Paramètres!B18 -> Non | C28: =IF(B28<>"Oui","",IF(_xlfn.MAXIFS(Réservations!$G$4:$G$303,Réservations!$B$4:$B$303,A28)=0,"",_xlfn.MAXIFS(Réservations!$G$4:$G$303,Réservations!$B$4:$B$303,A28))) | D28: =IF(OR(B28<>"Oui",C28=""),"",MAX(0,TODAY()-C28)) | E28: =IF(OR(B28<>"Oui",D28=""),"",IF(D28>Paramètres!$B$23,"À relancer","OK"))

Sheet Réservations
A1: RÉSERVATIONS
A2: MG Hôte — Conciergerie · Location courte durée
A3: ID | B3: Bien | C3: Plateforme | D3: Client | E3: Téléphone | F3: Arrivée | G3: Départ | H3: Nuits | I3: Prix / nuit | J3: Total séjour | K3: % comm. plateforme | L3: Comm. plateforme | M3: % frais MG Hôte | N3: Frais MG Hôte | O3: Net propriétaire | P3: Statut | Q3: Payé | R3: Ménage | S3: Notes | T3: Mois | U3: Année
A4: R-001 | B4: Bien 1 | C4: Airbnb | D4: Karim Benjelloun (exemple) | E4: +212 6 00 00 00 00 | F4: 46213 | G4: 46217 | H4: =IF(OR(F4="",G4=""),"",G4-F4) -> 4 | I4: 650 | J4: =IF(OR(H4="",I4=""),"",H4*I4) -> 2600 | K4: =IF(C4="","",IFERROR(INDEX(Paramètres!$E$9:$E$11,MATCH(C4,Paramètres!$D$9:$D$11,0)),0)) -> 0.03 | L4: =IF(J4="","",J4*K4) -> 78 | M4: =IF(B4="","",IFERROR(INDEX(Propriétaires!$E$4:$E$13,MATCH(B4,Propriétaires!$A$4:$A$13,0)),0.2)) -> 0.2 | N4: =IF(J4="","",(J4-L4)*M4) -> 504.4 | O4: =IF(J4="","",J4-L4-N4) -> 2017.6 | P4: Terminée | Q4: Oui | R4: Fait | S4: Ligne exemple — à remplacer | T4: =IF(F4="","",MONTH(F4)) -> 7 | U4: =IF(F4="","",YEAR(F4)) -> 2026
A5: R-002 | B5: Bien 1 | C5: Booking | D5: Sarah Martin (exemple) | E5: +33 6 00 00 00 00 | F5: 46224 | G5: 46228 | H5: =IF(OR(F5="",G5=""),"",G5-F5) -> 4 | I5: 700 | J5: =IF(OR(H5="",I5=""),"",H5*I5) -> 2800 | K5: =IF(C5="","",IFERROR(INDEX(Paramètres!$E$9:$E$11,MATCH(C5,Paramètres!$D$9:$D$11,0)),0)) -> 0.15 | L5: =IF(J5="","",J5*K5) -> 420 | M5: =IF(B5="","",IFERROR(INDEX(Propriétaires!$E$4:$E$13,MATCH(B5,Propriétaires!$A$4:$A$13,0)),0.2)) -> 0.2 | N5: =IF(J5="","",(J5-L5)*M5) -> 476 | O5: =IF(J5="","",J5-L5-N5) -> 1904 | P5: Confirmée | Q5: Non | R5: En attente | S5: Ligne exemple — à remplacer | T5: =IF(F5="","",MONTH(F5)) -> 7 | U5: =IF(F5="","",YEAR(F5)) -> 2026
H6: =IF(OR(F6="",G6=""),"",G6-F6) | J6: =IF(OR(H6="",I6=""),"",H6*I6) | K6: =IF(C6="","",IFERROR(INDEX(Paramètres!$E$9:$E$11,MATCH(C6,Paramètres!$D$9:$D$11,0)),0)) | L6: =IF(J6="","",J6*K6) | M6: =IF(B6="","",IFERROR(INDEX(Propriétaires!$E$4:$E$13,MATCH(B6,Propriétaires!$A$4:$A$13,0)),0.2)) | N6: =IF(J6="","",(J6-L6)*M6) | O6: =IF(J6="","",J6-L6-N6) | T6: =IF(F6="","",MONTH(F6)) | U6: =IF(F6="","",YEAR(F6))
H7: =IF(OR(F7="",G7=""),"",G7-F7) | J7: =IF(OR(H7="",I7=""),"",H7*I7) | K7: =IF(C7="","",IFERROR(INDEX(Paramètres!$E$9:$E$11,MATCH(C7,Paramètres!$D$9:$D$11,0)),0)) | L7: =IF(J7="","",J7*K7) | M7: =IF(B7="","",IFERROR(INDEX(Propriétaires!$E$4:$E$13,MATCH(B7,Propriétaires!$A$4:$A$13,0)),0.2)) | N7: =IF(J7="","",(J7-L7)*M7) | O7: =IF(J7="","",J7-L7-N7) | T7: =IF(F7="","",MONTH(F7)) | U7: =IF(F7="","",YEAR(F7))
H8: =IF(OR(F8="",G8=""),"",G8-F8) | J8: =IF(OR(H8="",I8=""),"",H8*I8) | K8: =IF(C8="","",IFERROR(INDEX(Paramètres!$E$9:$E$11,MATCH(C8,Paramètres!$D$9:$D$11,0)),0)) | L8: =IF(J8="","",J8*K8) | M8: =IF(B8="","",IFERROR(INDEX(Propriétaires!$E$4:$E$13,MATCH(B8,Propriétaires!$A$4:$A$13,0)),0.2)) | N8: =IF(J8="","",(J8-L8)*M8) | O8: =IF(J8="","",J8-L8-N8) | T8: =IF(F8="","",MONTH(F8)) | U8: =IF(F8="","",YEAR(F8))
H9: =IF(OR(F9="",G9=""),"",G9-F9) | J9: =IF(OR(H9="",I9=""),"",H9*I9) | K9: =IF(C9="","",IFERROR(INDEX(Paramètres!$E$9:$E$11,MATCH(C9,Paramètres!$D$9:$D$11,0)),0)) | L9: =IF(J9="","",J9*K9) | M9: =IF(B9="","",IFERROR(INDEX(Propriétaires!$E$4:$E$13,MATCH(B9,Propriétaires!$A$4:$A$13,0)),0.2)) | N9: =IF(J9="","",(J9-L9)*M9) | O9: =IF(J9="","",J9-L9-N9) | T9: =IF(F9="","",MONTH(F9)) | U9: =IF(F9="","",YEAR(F9))
H10: =IF(OR(F10="",G10=""),"",G10-F10) | J10: =IF(OR(H10="",I10=""),"",H10*I10) | K10: =IF(C10="","",IFERROR(INDEX(Paramètres!$E$9:$E$11,MATCH(C10,Paramètres!$D$9:$D$11,0)),0)) | L10: =IF(J10="","",J10*K10) | M10: =IF(B10="","",IFERROR(INDEX(Propriétaires!$E$4:$E$13,MATCH(B10,Propriétaires!$A$4:$A$13,0)),0.2)) | N10: =IF(J10="","",(J10-L10)*M10) | O10: =IF(J10="","",J10-L10-N10) | T10: =IF(F10="","",MONTH(F10)) | U10: =IF(F10="","",YEAR(F10))
H11: =IF(OR(F11="",G11=""),"",G11-F11) | J11: =IF(OR(H11="",I11=""),"",H11*I11) | K11: =IF(C11="","",IFERROR(INDEX(Paramètres!$E$9:$E$11,MATCH(C11,Paramètres!$D$9:$D$11,0)),0)) | L11: =IF(J11="","",J11*K11) | M11: =IF(B11="","",IFERROR(INDEX(Propriétaires!$E$4:$E$13,MATCH(B11,Propriétaires!$A$4:$A$13,0)),0.2)) | N11: =IF(J11="","",(J11-L11)*M11) | O11: =IF(J11="","",J11-L11-N11) | T11: =IF(F11="","",MONTH(F11)) | U11: =IF(F11="","",YEAR(F11))
H12: =IF(OR(F12="",G12=""),"",G12-F12) | J12: =IF(OR(H12="",I12=""),"",H12*I12) | K12: =IF(C12="","",IFERROR(INDEX(Paramètres!$E$9:$E$11,MATCH(C12,Paramètres!$D$9:$D$11,0)),0)) | L12: =IF(J12="","",J12*K12) | M12: =IF(B12="","",IFERROR(INDEX(Propriétaires!$E$4:$E$13,MATCH(B12,Propriétaires!$A$4:$A$13,0)),0.2)) | N12: =IF(J12="","",(J12-L12)*M12) | O12: =IF(J12="","",J12-L12-N12) | T12: =IF(F12="","",MONTH(F12)) | U12: =IF(F12="","",YEAR(F12))
H13: =IF(OR(F13="",G13=""),"",G13-F13) | J13: =IF(OR(H13="",I13=""),"",H13*I13) | K13: =IF(C13="","",IFERROR(INDEX(Paramètres!$E$9:$E$11,MATCH(C13,Paramètres!$D$9:$D$11,0)),0)) | L13: =IF(J13="","",J13*K13) | M13: =IF(B13="","",IFERROR(INDEX(Propriétaires!$E$4:$E$13,MATCH(B13,Propriétaires!$A$4:$A$13,0)),0.2)) | N13: =IF(J13="","",(J13-L13)*M13) | O13: =IF(J13="","",J13-L13-N13) | T13: =IF(F13="","",MONTH(F13)) | U13: =IF(F13="","",YEAR(F13))
H14: =IF(OR(F14="",G14=""),"",G14-F14) | J14: =IF(OR(H14="",I14=""),"",H14*I14) | K14: =IF(C14="","",IFERROR(INDEX(Paramètres!$E$9:$E$11,MATCH(C14,Paramètres!$D$9:$D$11,0)),0)) | L14: =IF(J14="","",J14*K14) | M14: =IF(B14="","",IFERROR(INDEX(Propriétaires!$E$4:$E$13,MATCH(B14,Propriétaires!$A$4:$A$13,0)),0.2)) | N14: =IF(J14="","",(J14-L14)*M14) | O14: =IF(J14="","",J14-L14-N14) | T14: =IF(F14="","",MONTH(F14)) | U14: =IF(F14="","",YEAR(F14))
H15: =IF(OR(F15="",G15=""),"",G15-F15) | J15: =IF(OR(H15="",I15=""),"",H15*I15) | K15: =IF(C15="","",IFERROR(INDEX(Paramètres!$E$9:$E$11,MATCH(C15,Paramètres!$D$9:$D$11,0)),0)) | L15: =IF(J15="","",J15*K15) | M15: =IF(B15="","",IFERROR(INDEX(Propriétaires!$E$4:$E$13,MATCH(B15,Propriétaires!$A$4:$A$13,0)),0.2)) | N15: =IF(J15="","",(J15-L15)*M15) | O15: =IF(J15="","",J15-L15-N15) | T15: =IF(F15="","",MONTH(F15)) | U15: =IF(F15="","",YEAR(F15))
H16: =IF(OR(F16="",G16=""),"",G16-F16) | J16: =IF(OR(H16="",I16=""),"",H16*I16) | K16: =IF(C16="","",IFERROR(INDEX(Paramètres!$E$9:$E$11,MATCH(C16,Paramètres!$D$9:$D$11,0)),0)) | L16: =IF(J16="","",J16*K16) | M16: =IF(B16="","",IFERROR(INDEX(Propriétaires!$E$4:$E$13,MATCH(B16,Propriétaires!$A$4:$A$13,0)),0.2)) | N16: =IF(J16="","",(J16-L16)*M16) | O16: =IF(J16="","",J16-L16-N16) | T16: =IF(F16="","",MONTH(F16)) | U16: =IF(F16="","",YEAR(F16))
H17: =IF(OR(F17="",G17=""),"",G17-F17) | J17: =IF(OR(H17="",I17=""),"",H17*I17) | K17: =IF(C17="","",IFERROR(INDEX(Paramètres!$E$9:$E$11,MATCH(C17,Paramètres!$D$9:$D$11,0)),0)) | L17: =IF(J17="","",J17*K17) | M17: =IF(B17="","",IFERROR(INDEX(Propriétaires!$E$4:$E$13,MATCH(B17,Propriétaires!$A$4:$A$13,0)),0.2)) | N17: =IF(J17="","",(J17-L17)*M17) | O17: =IF(J17="","",J17-L17-N17) | T17: =IF(F17="","",MONTH(F17)) | U17: =IF(F17="","",YEAR(F17))
... H303: =IF(OR(F303="",G303=""),"",G303-F303) | J303: =IF(OR(H303="",I303=""),"",H303*I303) | K303: =IF(C303="","",IFERROR(INDEX(Paramètres!$E$9:$E$11,MATCH(C303,Paramètres!$D$9:$D$11,0)),0)) | L303: =IF(J303="","",J303*K303) | M303: =IF(B303="","",IFERROR(INDEX(Propriétaires!$E$4:$E$13,MATCH(B303,Propriétaires!$A$4:$A$13,0)),0.2)) | N303: =IF(J303="","",(J303-L303)*M303) | O303: =IF(J303="","",J303-L303-N303) | T303: =IF(F303="","",MONTH(F303)) | U303: =IF(F303="","",YEAR(F303))

Sheet Dépenses
A1: DÉPENSES
A2: MG Hôte — Conciergerie · Location courte durée
A3: Date | B3: Bien | C3: Catégorie | D3: Description | E3: Montant | F3: Mois | G3: Année
A4: 46208 | B4: Bien 1 | C4: Électricité | D4: Facture électricité juillet (exemple) | E4: 350 | F4: =IF(A4="","",MONTH(A4)) -> 7 | G4: =IF(A4="","",YEAR(A4)) -> 2026
A5: 46215 | B5: Bien 1 | C5: Consommables | D5: Produits d'accueil + ménage (exemple) | E5: 180 | F5: =IF(A5="","",MONTH(A5)) -> 7 | G5: =IF(A5="","",YEAR(A5)) -> 2026
F6: =IF(A6="","",MONTH(A6)) | G6: =IF(A6="","",YEAR(A6))
F7: =IF(A7="","",MONTH(A7)) | G7: =IF(A7="","",YEAR(A7))
F8: =IF(A8="","",MONTH(A8)) | G8: =IF(A8="","",YEAR(A8))
F9: =IF(A9="","",MONTH(A9)) | G9: =IF(A9="","",YEAR(A9))
F10: =IF(A10="","",MONTH(A10)) | G10: =IF(A10="","",YEAR(A10))
F11: =IF(A11="","",MONTH(A11)) | G11: =IF(A11="","",YEAR(A11))
F12: =IF(A12="","",MONTH(A12)) | G12: =IF(A12="","",YEAR(A12))
F13: =IF(A13="","",MONTH(A13)) | G13: =IF(A13="","",YEAR(A13))
F14: =IF(A14="","",MONTH(A14)) | G14: =IF(A14="","",YEAR(A14))
F15: =IF(A15="","",MONTH(A15)) | G15: =IF(A15="","",YEAR(A15))
F16: =IF(A16="","",MONTH(A16)) | G16: =IF(A16="","",YEAR(A16))
F17: =IF(A17="","",MONTH(A17)) | G17: =IF(A17="","",YEAR(A17))
... F303: =IF(A303="","",MONTH(A303)) | G303: =IF(A303="","",YEAR(A303))

Sheet Ménage
A1: MÉNAGE
A2: MG Hôte — Conciergerie · Location courte durée
A3: Date | B3: Bien | C3: ID Réservation | D3: Statut | E3: Compte rendu
A4: 46217 | B4: Bien 1 | C4: R-001 | D4: Fait | E4: RAS — linge changé, stock produits OK (exemple)
A5: 46224 | B5: Bien 1 | C5: R-002 | D5: En attente

Sheet Incidents
A1: INCIDENTS / MAINTENANCE
A2: MG Hôte — Conciergerie · Location courte durée
A3: Date | B3: Bien | C3: Description | D3: Priorité | E3: Statut | F3: Coût | G3: Date résolution
A4: 46215 | B4: Bien 1 | C4: Fuite robinet salle de bain (exemple) | D4: Moyenne | E4: En cours | F4: 150

Sheet Propriétaires
A1: PROPRIÉTAIRES
A2: MG Hôte — Conciergerie · Location courte durée
A3: Bien | B3: Nom du propriétaire | C3: Téléphone | D3: Email | E3: % frais MG Hôte | F3: RIB / IBAN | G3: Notes
A4: Bien 1 | B4: Nom du propriétaire (exemple) | C4: +212 6 11 11 11 11 | D4: proprietaire@email.com | E4: 0.2
A5: Bien 2 | E5: 0.2
A6: Bien 3 | E6: 0.2
A7: Bien 4 | E7: 0.2
A8: Bien 5 | E8: 0.2
A9: Bien 6 | E9: 0.2
A10: Bien 7 | E10: 0.2
A11: Bien 8 | E11: 0.2
A12: Bien 9 | E12: 0.2
A13: Bien 10 | E13: 0.2

Sheet Synthèse
A1: SYNTHÈSE MENSUELLE
A2: Année suivie : voir l'onglet Paramètres (cellule B4)
A3: Mois | B3: Nuits | C3: Taux occup. | D3: CA brut | E3: Comm. plateformes | F3: Revenus MG Hôte | G3: Net propriétaires | H3: Maintenance | I3: Consommables | J3: Électricité | K3: Eau | L3: Publicité | M3: Autre | N3: Total dépenses | O3: Résultat MG Hôte | P3: Évolution CA
A4: Janvier | B4: =SUMIFS(Réservations!$H$4:$H$303,Réservations!$T$4:$T$303,$Q4,Réservations!$U$4:$U$303,Paramètres!$B$4,Réservations!$P$4:$P$303,"<>Annulée") -> 0 | C4: =IF(Paramètres!$B$20=0,0,B4/(DAY(DATE(Paramètres!$B$4,$Q4+1,0))*Paramètres!$B$20)) -> 0 | D4: =SUMIFS(Réservations!$J$4:$J$303,Réservations!$T$4:$T$303,$Q4,Réservations!$U$4:$U$303,Paramètres!$B$4,Réservations!$P$4:$P$303,"<>Annulée") -> 0 | E4: =SUMIFS(Réservations!$L$4:$L$303,Réservations!$T$4:$T$303,$Q4,Réservations!$U$4:$U$303,Paramètres!$B$4,Réservations!$P$4:$P$303,"<>Annulée") -> 0 | F4: =SUMIFS(Réservations!$N$4:$N$303,Réservations!$T$4:$T$303,$Q4,Réservations!$U$4:$U$303,Paramètres!$B$4,Réservations!$P$4:$P$303,"<>Annulée") -> 0 | G4: =SUMIFS(Réservations!$O$4:$O$303,Réservations!$T$4:$T$303,$Q4,Réservations!$U$4:$U$303,Paramètres!$B$4,Réservations!$P$4:$P$303,"<>Annulée") -> 0 | H4: =SUMIFS(Dépenses!$E$4:$E$303,Dépenses!$F$4:$F$303,$Q4,Dépenses!$G$4:$G$303,Paramètres!$B$4,Dépenses!$C$4:$C$303,"Maintenance") -> 0 | I4: =SUMIFS(Dépenses!$E$4:$E$303,Dépenses!$F$4:$F$303,$Q4,Dépenses!$G$4:$G$303,Paramètres!$B$4,Dépenses!$C$4:$C$303,"Consommables") -> 0 | J4: =SUMIFS(Dépenses!$E$4:$E$303,Dépenses!$F$4:$F$303,$Q4,Dépenses!$G$4:$G$303,Paramètres!$B$4,Dépenses!$C$4:$C$303,"Électricité") -> 0 | K4: =SUMIFS(Dépenses!$E$4:$E$303,Dépenses!$F$4:$F$303,$Q4,Dépenses!$G$4:$G$303,Paramètres!$B$4,Dépenses!$C$4:$C$303,"Eau") -> 0 | L4: =SUMIFS(Dépenses!$E$4:$E$303,Dépenses!$F$4:$F$303,$Q4,Dépenses!$G$4:$G$303,Paramètres!$B$4,Dépenses!$C$4:$C$303,"Publicité") -> 0 | M4: =SUMIFS(Dépenses!$E$4:$E$303,Dépenses!$F$4:$F$303,$Q4,Dépenses!$G$4:$G$303,Paramètres!$B$4,Dépenses!$C$4:$C$303,"Autre") -> 0 | N4: =SUM(H4:M4) -> 0 | O4: =F4-N4 -> 0 | P4: =IF($Q4=1,"",IF(D3=0,"",D4/D3-1)) | Q4: 1
A5: Février | B5: =SUMIFS(Réservations!$H$4:$H$303,Réservations!$T$4:$T$303,$Q5,Réservations!$U$4:$U$303,Paramètres!$B$4,Réservations!$P$4:$P$303,"<>Annulée") -> 0 | C5: =IF(Paramètres!$B$20=0,0,B5/(DAY(DATE(Paramètres!$B$4,$Q5+1,0))*Paramètres!$B$20)) -> 0 | D5: =SUMIFS(Réservations!$J$4:$J$303,Réservations!$T$4:$T$303,$Q5,Réservations!$U$4:$U$303,Paramètres!$B$4,Réservations!$P$4:$P$303,"<>Annulée") -> 0 | E5: =SUMIFS(Réservations!$L$4:$L$303,Réservations!$T$4:$T$303,$Q5,Réservations!$U$4:$U$303,Paramètres!$B$4,Réservations!$P$4:$P$303,"<>Annulée") -> 0 | F5: =SUMIFS(Réservations!$N$4:$N$303,Réservations!$T$4:$T$303,$Q5,Réservations!$U$4:$U$303,Paramètres!$B$4,Réservations!$P$4:$P$303,"<>Annulée") -> 0 | G5: =SUMIFS(Réservations!$O$4:$O$303,Réservations!$T$4:$T$303,$Q5,Réservations!$U$4:$U$303,Paramètres!$B$4,Réservations!$P$4:$P$303,"<>Annulée") -> 0 | H5: =SUMIFS(Dépenses!$E$4:$E$303,Dépenses!$F$4:$F$303,$Q5,Dépenses!$G$4:$G$303,Paramètres!$B$4,Dépenses!$C$4:$C$303,"Maintenance") -> 0 | I5: =SUMIFS(Dépenses!$E$4:$E$303,Dépenses!$F$4:$F$303,$Q5,Dépenses!$G$4:$G$303,Paramètres!$B$4,Dépenses!$C$4:$C$303,"Consommables") -> 0 | J5: =SUMIFS(Dépenses!$E$4:$E$303,Dépenses!$F$4:$F$303,$Q5,Dépenses!$G$4:$G$303,Paramètres!$B$4,Dépenses!$C$4:$C$303,"Électricité") -> 0 | K5: =SUMIFS(Dépenses!$E$4:$E$303,Dépenses!$F$4:$F$303,$Q5,Dépenses!$G$4:$G$303,Paramètres!$B$4,Dépenses!$C$4:$C$303,"Eau") -> 0 | L5: =SUMIFS(Dépenses!$E$4:$E$303,Dépenses!$F$4:$F$303,$Q5,Dépenses!$G$4:$G$303,Paramètres!$B$4,Dépenses!$C$4:$C$303,"Publicité") -> 0 | M5: =SUMIFS(Dépenses!$E$4:$E$303,Dépenses!$F$4:$F$303,$Q5,Dépenses!$G$4:$G$303,Paramètres!$B$4,Dépenses!$C$4:$C$303,"Autre") -> 0 | N5: =SUM(H5:M5) -> 0 | O5: =F5-N5 -> 0 | P5: =IF($Q5=1,"",IF(D4=0,"",D5/D4-1)) | Q5: 2
A6: Mars | B6: =SUMIFS(Réservations!$H$4:$H$303,Réservations!$T$4:$T$303,$Q6,Réservations!$U$4:$U$303,Paramètres!$B$4,Réservations!$P$4:$P$303,"<>Annulée") -> 0 | C6: =IF(Paramètres!$B$20=0,0,B6/(DAY(DATE(Paramètres!$B$4,$Q6+1,0))*Paramètres!$B$20)) -> 0 | D6: =SUMIFS(Réservations!$J$4:$J$303,Réservations!$T$4:$T$303,$Q6,Réservations!$U$4:$U$303,Paramètres!$B$4,Réservations!$P$4:$P$303,"<>Annulée") -> 0 | E6: =SUMIFS(Réservations!$L$4:$L$303,Réservations!$T$4:$T$303,$Q6,Réservations!$U$4:$U$303,Paramètres!$B$4,Réservations!$P$4:$P$303,"<>Annulée") -> 0 | F6: =SUMIFS(Réservations!$N$4:$N$303,Réservations!$T$4:$T$303,$Q6,Réservations!$U$4:$U$303,Paramètres!$B$4,Réservations!$P$4:$P$303,"<>Annulée") -> 0 | G6: =SUMIFS(Réservations!$O$4:$O$303,Réservations!$T$4:$T$303,$Q6,Réservations!$U$4:$U$303,Paramètres!$B$4,Réservations!$P$4:$P$303,"<>Annulée") -> 0 | H6: =SUMIFS(Dépenses!$E$4:$E$303,Dépenses!$F$4:$F$303,$Q6,Dépenses!$G$4:$G$303,Paramètres!$B$4,Dépenses!$C$4:$C$303,"Maintenance") -> 0 | I6: =SUMIFS(Dépenses!$E$4:$E$303,Dépenses!$F$4:$F$303,$Q6,Dépenses!$G$4:$G$303,Paramètres!$B$4,Dépenses!$C$4:$C$303,"Consommables") -> 0 | J6: =SUMIFS(Dépenses!$E$4:$E$303,Dépenses!$F$4:$F$303,$Q6,Dépenses!$G$4:$G$303,Paramètres!$B$4,Dépenses!$C$4:$C$303,"Électricité") -> 0 | K6: =SUMIFS(Dépenses!$E$4:$E$303,Dépenses!$F$4:$F$303,$Q6,Dépenses!$G$4:$G$303,Paramètres!$B$4,Dépenses!$C$4:$C$303,"Eau") -> 0 | L6: =SUMIFS(Dépenses!$E$4:$E$303,Dépenses!$F$4:$F$303,$Q6,Dépenses!$G$4:$G$303,Paramètres!$B$4,Dépenses!$C$4:$C$303,"Publicité") -> 0 | M6: =SUMIFS(Dépenses!$E$4:$E$303,Dépenses!$F$4:$F$303,$Q6,Dépenses!$G$4:$G$303,Paramètres!$B$4,Dépenses!$C$4:$C$303,"Autre") -> 0 | N6: =SUM(H6:M6) -> 0 | O6: =F6-N6 -> 0 | P6: =IF($Q6=1,"",IF(D5=0,"",D6/D5-1)) | Q6: 3
A7: Avril | B7: =SUMIFS(Réservations!$H$4:$H$303,Réservations!$T$4:$T$303,$Q7,Réservations!$U$4:$U$303,Paramètres!$B$4,Réservations!$P$4:$P$303,"<>Annulée") -> 0 | C7: =IF(Paramètres!$B$20=0,0,B7/(DAY(DATE(Paramètres!$B$4,$Q7+1,0))*Paramètres!$B$20)) -> 0 | D7: =SUMIFS(Réservations!$J$4:$J$303,Réservations!$T$4:$T$303,$Q7,Réservations!$U$4:$U$303,Paramètres!$B$4,Réservations!$P$4:$P$303,"<>Annulée") -> 0 | E7: =SUMIFS(Réservations!$L$4:$L$303,Réservations!$T$4:$T$303,$Q7,Réservations!$U$4:$U$303,Paramètres!$B$4,Réservations!$P$4:$P$303,"<>Annulée") -> 0 | F7: =SUMIFS(Réservations!$N$4:$N$303,Réservations!$T$4:$T$303,$Q7,Réservations!$U$4:$U$303,Paramètres!$B$4,Réservations!$P$4:$P$303,"<>Annulée") -> 0 | G7: =SUMIFS(Réservations!$O$4:$O$303,Réservations!$T$4:$T$303,$Q7,Réservations!$U$4:$U$303,Paramètres!$B$4,Réservations!$P$4:$P$303,"<>Annulée") -> 0 | H7: =SUMIFS(Dépenses!$E$4:$E$303,Dépenses!$F$4:$F$303,$Q7,Dépenses!$G$4:$G$303,Paramètres!$B$4,Dépenses!$C$4:$C$303,"Maintenance") -> 0 | I7: =SUMIFS(Dépenses!$E$4:$E$303,Dépenses!$F$4:$F$303,$Q7,Dépenses!$G$4:$G$303,Paramètres!$B$4,Dépenses!$C$4:$C$303,"Consommables") -> 0 | J7: =SUMIFS(Dépenses!$E$4:$E$303,Dépenses!$F$4:$F$303,$Q7,Dépenses!$G$4:$G$303,Paramètres!$B$4,Dépenses!$C$4:$C$303,"Électricité") -> 0 | K7: =SUMIFS(Dépenses!$E$4:$E$303,Dépenses!$F$4:$F$303,$Q7,Dépenses!$G$4:$G$303,Paramètres!$B$4,Dépenses!$C$4:$C$303,"Eau") -> 0 | L7: =SUMIFS(Dépenses!$E$4:$E$303,Dépenses!$F$4:$F$303,$Q7,Dépenses!$G$4:$G$303,Paramètres!$B$4,Dépenses!$C$4:$C$303,"Publicité") -> 0 | M7: =SUMIFS(Dépenses!$E$4:$E$303,Dépenses!$F$4:$F$303,$Q7,Dépenses!$G$4:$G$303,Paramètres!$B$4,Dépenses!$C$4:$C$303,"Autre") -> 0 | N7: =SUM(H7:M7) -> 0 | O7: =F7-N7 -> 0 | P7: =IF($Q7=1,"",IF(D6=0,"",D7/D6-1)) | Q7: 4
A8: Mai | B8: =SUMIFS(Réservations!$H$4:$H$303,Réservations!$T$4:$T$303,$Q8,Réservations!$U$4:$U$303,Paramètres!$B$4,Réservations!$P$4:$P$303,"<>Annulée") -> 0 | C8: =IF(Paramètres!$B$20=0,0,B8/(DAY(DATE(Paramètres!$B$4,$Q8+1,0))*Paramètres!$B$20)) -> 0 | D8: =SUMIFS(Réservations!$J$4:$J$303,Réservations!$T$4:$T$303,$Q8,Réservations!$U$4:$U$303,Paramètres!$B$4,Réservations!$P$4:$P$303,"<>Annulée") -> 0 | E8: =SUMIFS(Réservations!$L$4:$L$303,Réservations!$T$4:$T$303,$Q8,Réservations!$U$4:$U$303,Paramètres!$B$4,Réservations!$P$4:$P$303,"<>Annulée") -> 0 | F8: =SUMIFS(Réservations!$N$4:$N$303,Réservations!$T$4:$T$303,$Q8,Réservations!$U$4:$U$303,Paramètres!$B$4,Réservations!$P$4:$P$303,"<>Annulée") -> 0 | G8: =SUMIFS(Réservations!$O$4:$O$303,Réservations!$T$4:$T$303,$Q8,Réservations!$U$4:$U$303,Paramètres!$B$4,Réservations!$P$4:$P$303,"<>Annulée") -> 0 | H8: =SUMIFS(Dépenses!$E$4:$E$303,Dépenses!$F$4:$F$303,$Q8,Dépenses!$G$4:$G$303,Paramètres!$B$4,Dépenses!$C$4:$C$303,"Maintenance") -> 0 | I8: =SUMIFS(Dépenses!$E$4:$E$303,Dépenses!$F$4:$F$303,$Q8,Dépenses!$G$4:$G$303,Paramètres!$B$4,Dépenses!$C$4:$C$303,"Consommables") -> 0 | J8: =SUMIFS(Dépenses!$E$4:$E$303,Dépenses!$F$4:$F$303,$Q8,Dépenses!$G$4:$G$303,Paramètres!$B$4,Dépenses!$C$4:$C$303,"Électricité") -> 0 | K8: =SUMIFS(Dépenses!$E$4:$E$303,Dépenses!$F$4:$F$303,$Q8,Dépenses!$G$4:$G$303,Paramètres!$B$4,Dépenses!$C$4:$C$303,"Eau") -> 0 | L8: =SUMIFS(Dépenses!$E$4:$E$303,Dépenses!$F$4:$F$303,$Q8,Dépenses!$G$4:$G$303,Paramètres!$B$4,Dépenses!$C$4:$C$303,"Publicité") -> 0 | M8: =SUMIFS(Dépenses!$E$4:$E$303,Dépenses!$F$4:$F$303,$Q8,Dépenses!$G$4:$G$303,Paramètres!$B$4,Dépenses!$C$4:$C$303,"Autre") -> 0 | N8: =SUM(H8:M8) -> 0 | O8: =F8-N8 -> 0 | P8: =IF($Q8=1,"",IF(D7=0,"",D8/D7-1)) | Q8: 5
A9: Juin | B9: =SUMIFS(Réservations!$H$4:$H$303,Réservations!$T$4:$T$303,$Q9,Réservations!$U$4:$U$303,Paramètres!$B$4,Réservations!$P$4:$P$303,"<>Annulée") -> 0 | C9: =IF(Paramètres!$B$20=0,0,B9/(DAY(DATE(Paramètres!$B$4,$Q9+1,0))*Paramètres!$B$20)) -> 0 | D9: =SUMIFS(Réservations!$J$4:$J$303,Réservations!$T$4:$T$303,$Q9,Réservations!$U$4:$U$303,Paramètres!$B$4,Réservations!$P$4:$P$303,"<>Annulée") -> 0 | E9: =SUMIFS(Réservations!$L$4:$L$303,Réservations!$T$4:$T$303,$Q9,Réservations!$U$4:$U$303,Paramètres!$B$4,Réservations!$P$4:$P$303,"<>Annulée") -> 0 | F9: =SUMIFS(Réservations!$N$4:$N$303,Réservations!$T$4:$T$303,$Q9,Réservations!$U$4:$U$303,Paramètres!$B$4,Réservations!$P$4:$P$303,"<>Annulée") -> 0 | G9: =SUMIFS(Réservations!$O$4:$O$303,Réservations!$T$4:$T$303,$Q9,Réservations!$U$4:$U$303,Paramètres!$B$4,Réservations!$P$4:$P$303,"<>Annulée") -> 0 | H9: =SUMIFS(Dépenses!$E$4:$E$303,Dépenses!$F$4:$F$303,$Q9,Dépenses!$G$4:$G$303,Paramètres!$B$4,Dépenses!$C$4:$C$303,"Maintenance") -> 0 | I9: =SUMIFS(Dépenses!$E$4:$E$303,Dépenses!$F$4:$F$303,$Q9,Dépenses!$G$4:$G$303,Paramètres!$B$4,Dépenses!$C$4:$C$303,"Consommables") -> 0 | J9: =SUMIFS(Dépenses!$E$4:$E$303,Dépenses!$F$4:$F$303,$Q9,Dépenses!$G$4:$G$303,Paramètres!$B$4,Dépenses!$C$4:$C$303,"Électricité") -> 0 | K9: =SUMIFS(Dépenses!$E$4:$E$303,Dépenses!$F$4:$F$303,$Q9,Dépenses!$G$4:$G$303,Paramètres!$B$4,Dépenses!$C$4:$C$303,"Eau") -> 0 | L9: =SUMIFS(Dépenses!$E$4:$E$303,Dépenses!$F$4:$F$303,$Q9,Dépenses!$G$4:$G$303,Paramètres!$B$4,Dépenses!$C$4:$C$303,"Publicité") -> 0 | M9: =SUMIFS(Dépenses!$E$4:$E$303,Dépenses!$F$4:$F$303,$Q9,Dépenses!$G$4:$G$303,Paramètres!$B$4,Dépenses!$C$4:$C$303,"Autre") -> 0 | N9: =SUM(H9:M9) -> 0 | O9: =F9-N9 -> 0 | P9: =IF($Q9=1,"",IF(D8=0,"",D9/D8-1)) | Q9: 6
A10: Juillet | B10: =SUMIFS(Réservations!$H$4:$H$303,Réservations!$T$4:$T$303,$Q10,Réservations!$U$4:$U$303,Paramètres!$B$4,Réservations!$P$4:$P$303,"<>Annulée") -> 8 | C10: =IF(Paramètres!$B$20=0,0,B10/(DAY(DATE(Paramètres!$B$4,$Q10+1,0))*Paramètres!$B$20)) -> 0.25806452 | D10: =SUMIFS(Réservations!$J$4:$J$303,Réservations!$T$4:$T$303,$Q10,Réservations!$U$4:$U$303,Paramètres!$B$4,Réservations!$P$4:$P$303,"<>Annulée") -> 5400 | E10: =SUMIFS(Réservations!$L$4:$L$303,Réservations!$T$4:$T$303,$Q10,Réservations!$U$4:$U$303,Paramètres!$B$4,Réservations!$P$4:$P$303,"<>Annulée") -> 498 | F10: =SUMIFS(Réservations!$N$4:$N$303,Réservations!$T$4:$T$303,$Q10,Réservations!$U$4:$U$303,Paramètres!$B$4,Réservations!$P$4:$P$303,"<>Annulée") -> 980.4 | G10: =SUMIFS(Réservations!$O$4:$O$303,Réservations!$T$4:$T$303,$Q10,Réservations!$U$4:$U$303,Paramètres!$B$4,Réservations!$P$4:$P$303,"<>Annulée") -> 3921.6 | H10: =SUMIFS(Dépenses!$E$4:$E$303,Dépenses!$F$4:$F$303,$Q10,Dépenses!$G$4:$G$303,Paramètres!$B$4,Dépenses!$C$4:$C$303,"Maintenance") -> 0 | I10: =SUMIFS(Dépenses!$E$4:$E$303,Dépenses!$F$4:$F$303,$Q10,Dépenses!$G$4:$G$303,Paramètres!$B$4,Dépenses!$C$4:$C$303,"Consommables") -> 180 | J10: =SUMIFS(Dépenses!$E$4:$E$303,Dépenses!$F$4:$F$303,$Q10,Dépenses!$G$4:$G$303,Paramètres!$B$4,Dépenses!$C$4:$C$303,"Électricité") -> 350 | K10: =SUMIFS(Dépenses!$E$4:$E$303,Dépenses!$F$4:$F$303,$Q10,Dépenses!$G$4:$G$303,Paramètres!$B$4,Dépenses!$C$4:$C$303,"Eau") -> 0 | L10: =SUMIFS(Dépenses!$E$4:$E$303,Dépenses!$F$4:$F$303,$Q10,Dépenses!$G$4:$G$303,Paramètres!$B$4,Dépenses!$C$4:$C$303,"Publicité") -> 0 | M10: =SUMIFS(Dépenses!$E$4:$E$303,Dépenses!$F$4:$F$303,$Q10,Dépenses!$G$4:$G$303,Paramètres!$B$4,Dépenses!$C$4:$C$303,"Autre") -> 0 | N10: =SUM(H10:M10) -> 530 | O10: =F10-N10 -> 450.4 | P10: =IF($Q10=1,"",IF(D9=0,"",D10/D9-1)) | Q10: 7
A11: Août | B11: =SUMIFS(Réservations!$H$4:$H$303,Réservations!$T$4:$T$303,$Q11,Réservations!$U$4:$U$303,Paramètres!$B$4,Réservations!$P$4:$P$303,"<>Annulée") -> 0 | C11: =IF(Paramètres!$B$20=0,0,B11/(DAY(DATE(Paramètres!$B$4,$Q11+1,0))*Paramètres!$B$20)) -> 0 | D11: =SUMIFS(Réservations!$J$4:$J$303,Réservations!$T$4:$T$303,$Q11,Réservations!$U$4:$U$303,Paramètres!$B$4,Réservations!$P$4:$P$303,"<>Annulée") -> 0 | E11: =SUMIFS(Réservations!$L$4:$L$303,Réservations!$T$4:$T$303,$Q11,Réservations!$U$4:$U$303,Paramètres!$B$4,Réservations!$P$4:$P$303,"<>Annulée") -> 0 | F11: =SUMIFS(Réservations!$N$4:$N$303,Réservations!$T$4:$T$303,$Q11,Réservations!$U$4:$U$303,Paramètres!$B$4,Réservations!$P$4:$P$303,"<>Annulée") -> 0 | G11: =SUMIFS(Réservations!$O$4:$O$303,Réservations!$T$4:$T$303,$Q11,Réservations!$U$4:$U$303,Paramètres!$B$4,Réservations!$P$4:$P$303,"<>Annulée") -> 0 | H11: =SUMIFS(Dépenses!$E$4:$E$303,Dépenses!$F$4:$F$303,$Q11,Dépenses!$G$4:$G$303,Paramètres!$B$4,Dépenses!$C$4:$C$303,"Maintenance") -> 0 | I11: =SUMIFS(Dépenses!$E$4:$E$303,Dépenses!$F$4:$F$303,$Q11,Dépenses!$G$4:$G$303,Paramètres!$B$4,Dépenses!$C$4:$C$303,"Consommables") -> 0 | J11: =SUMIFS(Dépenses!$E$4:$E$303,Dépenses!$F$4:$F$303,$Q11,Dépenses!$G$4:$G$303,Paramètres!$B$4,Dépenses!$C$4:$C$303,"Électricité") -> 0 | K11: =SUMIFS(Dépenses!$E$4:$E$303,Dépenses!$F$4:$F$303,$Q11,Dépenses!$G$4:$G$303,Paramètres!$B$4,Dépenses!$C$4:$C$303,"Eau") -> 0 | L11: =SUMIFS(Dépenses!$E$4:$E$303,Dépenses!$F$4:$F$303,$Q11,Dépenses!$G$4:$G$303,Paramètres!$B$4,Dépenses!$C$4:$C$303,"Publicité") -> 0 | M11: =SUMIFS(Dépenses!$E$4:$E$303,Dépenses!$F$4:$F$303,$Q11,Dépenses!$G$4:$G$303,Paramètres!$B$4,Dépenses!$C$4:$C$303,"Autre") -> 0 | N11: =SUM(H11:M11) -> 0 | O11: =F11-N11 -> 0 | P11: =IF($Q11=1,"",IF(D10=0,"",D11/D10-1)) -> -1 | Q11: 8
A12: Septembre | B12: =SUMIFS(Réservations!$H$4:$H$303,Réservations!$T$4:$T$303,$Q12,Réservations!$U$4:$U$303,Paramètres!$B$4,Réservations!$P$4:$P$303,"<>Annulée") -> 0 | C12: =IF(Paramètres!$B$20=0,0,B12/(DAY(DATE(Paramètres!$B$4,$Q12+1,0))*Paramètres!$B$20)) -> 0 | D12: =SUMIFS(Réservations!$J$4:$J$303,Réservations!$T$4:$T$303,$Q12,Réservations!$U$4:$U$303,Paramètres!$B$4,Réservations!$P$4:$P$303,"<>Annulée") -> 0 | E12: =SUMIFS(Réservations!$L$4:$L$303,Réservations!$T$4:$T$303,$Q12,Réservations!$U$4:$U$303,Paramètres!$B$4,Réservations!$P$4:$P$303,"<>Annulée") -> 0 | F12: =SUMIFS(Réservations!$N$4:$N$303,Réservations!$T$4:$T$303,$Q12,Réservations!$U$4:$U$303,Paramètres!$B$4,Réservations!$P$4:$P$303,"<>Annulée") -> 0 | G12: =SUMIFS(Réservations!$O$4:$O$303,Réservations!$T$4:$T$303,$Q12,Réservations!$U$4:$U$303,Paramètres!$B$4,Réservations!$P$4:$P$303,"<>Annulée") -> 0 | H12: =SUMIFS(Dépenses!$E$4:$E$303,Dépenses!$F$4:$F$303,$Q12,Dépenses!$G$4:$G$303,Paramètres!$B$4,Dépenses!$C$4:$C$303,"Maintenance") -> 0 | I12: =SUMIFS(Dépenses!$E$4:$E$303,Dépenses!$F$4:$F$303,$Q12,Dépenses!$G$4:$G$303,Paramètres!$B$4,Dépenses!$C$4:$C$303,"Consommables") -> 0 | J12: =SUMIFS(Dépenses!$E$4:$E$303,Dépenses!$F$4:$F$303,$Q12,Dépenses!$G$4:$G$303,Paramètres!$B$4,Dépenses!$C$4:$C$303,"Électricité") -> 0 | K12: =SUMIFS(Dépenses!$E$4:$E$303,Dépenses!$F$4:$F$303,$Q12,Dépenses!$G$4:$G$303,Paramètres!$B$4,Dépenses!$C$4:$C$303,"Eau") -> 0 | L12: =SUMIFS(Dépenses!$E$4:$E$303,Dépenses!$F$4:$F$303,$Q12,Dépenses!$G$4:$G$303,Paramètres!$B$4,Dépenses!$C$4:$C$303,"Publicité") -> 0 | M12: =SUMIFS(Dépenses!$E$4:$E$303,Dépenses!$F$4:$F$303,$Q12,Dépenses!$G$4:$G$303,Paramètres!$B$4,Dépenses!$C$4:$C$303,"Autre") -> 0 | N12: =SUM(H12:M12) -> 0 | O12: =F12-N12 -> 0 | P12: =IF($Q12=1,"",IF(D11=0,"",D12/D11-1)) | Q12: 9
A13: Octobre | B13: =SUMIFS(Réservations!$H$4:$H$303,Réservations!$T$4:$T$303,$Q13,Réservations!$U$4:$U$303,Paramètres!$B$4,Réservations!$P$4:$P$303,"<>Annulée") -> 0 | C13: =IF(Paramètres!$B$20=0,0,B13/(DAY(DATE(Paramètres!$B$4,$Q13+1,0))*Paramètres!$B$20)) -> 0 | D13: =SUMIFS(Réservations!$J$4:$J$303,Réservations!$T$4:$T$303,$Q13,Réservations!$U$4:$U$303,Paramètres!$B$4,Réservations!$P$4:$P$303,"<>Annulée") -> 0 | E13: =SUMIFS(Réservations!$L$4:$L$303,Réservations!$T$4:$T$303,$Q13,Réservations!$U$4:$U$303,Paramètres!$B$4,Réservations!$P$4:$P$303,"<>Annulée") -> 0 | F13: =SUMIFS(Réservations!$N$4:$N$303,Réservations!$T$4:$T$303,$Q13,Réservations!$U$4:$U$303,Paramètres!$B$4,Réservations!$P$4:$P$303,"<>Annulée") -> 0 | G13: =SUMIFS(Réservations!$O$4:$O$303,Réservations!$T$4:$T$303,$Q13,Réservations!$U$4:$U$303,Paramètres!$B$4,Réservations!$P$4:$P$303,"<>Annulée") -> 0 | H13: =SUMIFS(Dépenses!$E$4:$E$303,Dépenses!$F$4:$F$303,$Q13,Dépenses!$G$4:$G$303,Paramètres!$B$4,Dépenses!$C$4:$C$303,"Maintenance") -> 0 | I13: =SUMIFS(Dépenses!$E$4:$E$303,Dépenses!$F$4:$F$303,$Q13,Dépenses!$G$4:$G$303,Paramètres!$B$4,Dépenses!$C$4:$C$303,"Consommables") -> 0 | J13: =SUMIFS(Dépenses!$E$4:$E$303,Dépenses!$F$4:$F$303,$Q13,Dépenses!$G$4:$G$303,Paramètres!$B$4,Dépenses!$C$4:$C$303,"Électricité") -> 0 | K13: =SUMIFS(Dépenses!$E$4:$E$303,Dépenses!$F$4:$F$303,$Q13,Dépenses!$G$4:$G$303,Paramètres!$B$4,Dépenses!$C$4:$C$303,"Eau") -> 0 | L13: =SUMIFS(Dépenses!$E$4:$E$303,Dépenses!$F$4:$F$303,$Q13,Dépenses!$G$4:$G$303,Paramètres!$B$4,Dépenses!$C$4:$C$303,"Publicité") -> 0 | M13: =SUMIFS(Dépenses!$E$4:$E$303,Dépenses!$F$4:$F$303,$Q13,Dépenses!$G$4:$G$303,Paramètres!$B$4,Dépenses!$C$4:$C$303,"Autre") -> 0 | N13: =SUM(H13:M13) -> 0 | O13: =F13-N13 -> 0 | P13: =IF($Q13=1,"",IF(D12=0,"",D13/D12-1)) | Q13: 10
A14: Novembre | B14: =SUMIFS(Réservations!$H$4:$H$303,Réservations!$T$4:$T$303,$Q14,Réservations!$U$4:$U$303,Paramètres!$B$4,Réservations!$P$4:$P$303,"<>Annulée") -> 0 | C14: =IF(Paramètres!$B$20=0,0,B14/(DAY(DATE(Paramètres!$B$4,$Q14+1,0))*Paramètres!$B$20)) -> 0 | D14: =SUMIFS(Réservations!$J$4:$J$303,Réservations!$T$4:$T$303,$Q14,Réservations!$U$4:$U$303,Paramètres!$B$4,Réservations!$P$4:$P$303,"<>Annulée") -> 0 | E14: =SUMIFS(Réservations!$L$4:$L$303,Réservations!$T$4:$T$303,$Q14,Réservations!$U$4:$U$303,Paramètres!$B$4,Réservations!$P$4:$P$303,"<>Annulée") -> 0 | F14: =SUMIFS(Réservations!$N$4:$N$303,Réservations!$T$4:$T$303,$Q14,Réservations!$U$4:$U$303,Paramètres!$B$4,Réservations!$P$4:$P$303,"<>Annulée") -> 0 | G14: =SUMIFS(Réservations!$O$4:$O$303,Réservations!$T$4:$T$303,$Q14,Réservations!$U$4:$U$303,Paramètres!$B$4,Réservations!$P$4:$P$303,"<>Annulée") -> 0 | H14: =SUMIFS(Dépenses!$E$4:$E$303,Dépenses!$F$4:$F$303,$Q14,Dépenses!$G$4:$G$303,Paramètres!$B$4,Dépenses!$C$4:$C$303,"Maintenance") -> 0 | I14: =SUMIFS(Dépenses!$E$4:$E$303,Dépenses!$F$4:$F$303,$Q14,Dépenses!$G$4:$G$303,Paramètres!$B$4,Dépenses!$C$4:$C$303,"Consommables") -> 0 | J14: =SUMIFS(Dépenses!$E$4:$E$303,Dépenses!$F$4:$F$303,$Q14,Dépenses!$G$4:$G$303,Paramètres!$B$4,Dépenses!$C$4:$C$303,"Électricité") -> 0 | K14: =SUMIFS(Dépenses!$E$4:$E$303,Dépenses!$F$4:$F$303,$Q14,Dépenses!$G$4:$G$303,Paramètres!$B$4,Dépenses!$C$4:$C$303,"Eau") -> 0 | L14: =SUMIFS(Dépenses!$E$4:$E$303,Dépenses!$F$4:$F$303,$Q14,Dépenses!$G$4:$G$303,Paramètres!$B$4,Dépenses!$C$4:$C$303,"Publicité") -> 0 | M14: =SUMIFS(Dépenses!$E$4:$E$303,Dépenses!$F$4:$F$303,$Q14,Dépenses!$G$4:$G$303,Paramètres!$B$4,Dépenses!$C$4:$C$303,"Autre") -> 0 | N14: =SUM(H14:M14) -> 0 | O14: =F14-N14 -> 0 | P14: =IF($Q14=1,"",IF(D13=0,"",D14/D13-1)) | Q14: 11
A15: Décembre | B15: =SUMIFS(Réservations!$H$4:$H$303,Réservations!$T$4:$T$303,$Q15,Réservations!$U$4:$U$303,Paramètres!$B$4,Réservations!$P$4:$P$303,"<>Annulée") -> 0 | C15: =IF(Paramètres!$B$20=0,0,B15/(DAY(DATE(Paramètres!$B$4,$Q15+1,0))*Paramètres!$B$20)) -> 0 | D15: =SUMIFS(Réservations!$J$4:$J$303,Réservations!$T$4:$T$303,$Q15,Réservations!$U$4:$U$303,Paramètres!$B$4,Réservations!$P$4:$P$303,"<>Annulée") -> 0 | E15: =SUMIFS(Réservations!$L$4:$L$303,Réservations!$T$4:$T$303,$Q15,Réservations!$U$4:$U$303,Paramètres!$B$4,Réservations!$P$4:$P$303,"<>Annulée") -> 0 | F15: =SUMIFS(Réservations!$N$4:$N$303,Réservations!$T$4:$T$303,$Q15,Réservations!$U$4:$U$303,Paramètres!$B$4,Réservations!$P$4:$P$303,"<>Annulée") -> 0 | G15: =SUMIFS(Réservations!$O$4:$O$303,Réservations!$T$4:$T$303,$Q15,Réservations!$U$4:$U$303,Paramètres!$B$4,Réservations!$P$4:$P$303,"<>Annulée") -> 0 | H15: =SUMIFS(Dépenses!$E$4:$E$303,Dépenses!$F$4:$F$303,$Q15,Dépenses!$G$4:$G$303,Paramètres!$B$4,Dépenses!$C$4:$C$303,"Maintenance") -> 0 | I15: =SUMIFS(Dépenses!$E$4:$E$303,Dépenses!$F$4:$F$303,$Q15,Dépenses!$G$4:$G$303,Paramètres!$B$4,Dépenses!$C$4:$C$303,"Consommables") -> 0 | J15: =SUMIFS(Dépenses!$E$4:$E$303,Dépenses!$F$4:$F$303,$Q15,Dépenses!$G$4:$G$303,Paramètres!$B$4,Dépenses!$C$4:$C$303,"Électricité") -> 0 | K15: =SUMIFS(Dépenses!$E$4:$E$303,Dépenses!$F$4:$F$303,$Q15,Dépenses!$G$4:$G$303,Paramètres!$B$4,Dépenses!$C$4:$C$303,"Eau") -> 0 | L15: =SUMIFS(Dépenses!$E$4:$E$303,Dépenses!$F$4:$F$303,$Q15,Dépenses!$G$4:$G$303,Paramètres!$B$4,Dépenses!$C$4:$C$303,"Publicité") -> 0 | M15: =SUMIFS(Dépenses!$E$4:$E$303,Dépenses!$F$4:$F$303,$Q15,Dépenses!$G$4:$G$303,Paramètres!$B$4,Dépenses!$C$4:$C$303,"Autre") -> 0 | N15: =SUM(H15:M15) -> 0 | O15: =F15-N15 -> 0 | P15: =IF($Q15=1,"",IF(D14=0,"",D15/D14-1)) | Q15: 12
A16: TOTAL ANNÉE | B16: =SUM(B4:B15) -> 8 | C16: =IF(Paramètres!$B$20=0,0,B16/(365*Paramètres!$B$20)) -> 0.021917808 | D16: =SUM(D4:D15) -> 5400 | E16: =SUM(E4:E15) -> 498 | F16: =SUM(F4:F15) -> 980.4 | G16: =SUM(G4:G15) -> 3921.6 | H16: =SUM(H4:H15) -> 0 | I16: =SUM(I4:I15) -> 180 | J16: =SUM(J4:J15) -> 350 | K16: =SUM(K4:K15) -> 0 | ... O16: =SUM(O4:O15) -> 450.4

Sheet Facture
A1: MG HÔTE — FACTURE PROPRIÉTAIRE
A2: Conciergerie · Location courte durée
A4: MG Hôte — vos coordonnées : | B4: Adresse, ville — Tél : +212 ... — Email : contact@mghote.com
A6: N° de facture | B6: F-2026-001
A7: Date d'émission | B7: =TODAY() -> 46224
A8: Bien concerné | B8: Bien 1
A9: Mois (1 à 12) | B9: 7
A10: Année | B10: 2026
A12: Facturé à : | B12: =IFERROR(INDEX(Propriétaires!$B$4:$B$13,MATCH($B$8,Propriétaires!$A$4:$A$13,0)),"") -> Nom du propriétaire (exemple)
A13: Téléphone : | B13: =IFERROR(INDEX(Propriétaires!$C$4:$C$13,MATCH($B$8,Propriétaires!$A$4:$A$13,0)),"") -> +212 6 11 11 11 11
A14: Email : | B14: =IFERROR(INDEX(Propriétaires!$D$4:$D$13,MATCH($B$8,Propriétaires!$A$4:$A$13,0)),"") -> proprietaire@email.com
A16: Libellé | E16: Montant
A17: Chiffre d'affaires brut du mois | E17: =SUMIFS(Réservations!$J$4:$J$303,Réservations!$B$4:$B$303,$B$8,Réservations!$T$4:$T$303,$B$9,Réservations!$U$4:$U$303,$B$10,Réservations!$P$4:$P$303,"<>Annulée") -> 5400
A18: Commissions plateformes (Airbnb / Booking) | E18: =-SUMIFS(Réservations!$L$4:$L$303,Réservations!$B$4:$B$303,$B$8,Réservations!$T$4:$T$303,$B$9,Réservations!$U$4:$U$303,$B$10,Réservations!$P$4:$P$303,"<>Annulée") -> -498
A19: Frais de conciergerie MG Hôte | E19: =-SUMIFS(Réservations!$N$4:$N$303,Réservations!$B$4:$B$303,$B$8,Réservations!$T$4:$T$303,$B$9,Réservations!$U$4:$U$303,$B$10,Réservations!$P$4:$P$303,"<>Annulée") -> -980.4
A20: Dépenses du mois (refacturées au propriétaire) | E20: =-SUMIFS(Dépenses!$E$4:$E$303,Dépenses!$B$4:$B$303,$B$8,Dépenses!$F$4:$F$303,$B$9,Dépenses!$G$4:$G$303,$B$10) -> -530
A22: NET À VERSER AU PROPRIÉTAIRE | E22: =E17+E18+E19+E20 -> 3391.6
A24: Les dépenses refacturées sont détaillées dans l'onglet Dépenses (filtrer par bien et par mois).
A26: Merci de votre confiance — MG Hôte

Sheet Rapport
A1: MG HÔTE — RAPPORT MENSUEL
A2: État mensuel global — prêt à imprimer / exporter en PDF
A4: Mois (1 à 12) | B4: 7
A5: Année | B5: 2026
A7: ACTIVITÉ
A8: Réservations du mois | B8: =COUNTIFS(Réservations!$T$4:$T$303,$B$4,Réservations!$U$4:$U$303,$B$5,Réservations!$P$4:$P$303,"<>Annulée") -> 2
A9: Nuits réservées | B9: =SUMIFS(Réservations!$H$4:$H$303,Réservations!$T$4:$T$303,$B$4,Réservations!$U$4:$U$303,$B$5,Réservations!$P$4:$P$303,"<>Annulée") -> 8
A10: Taux d'occupation | B10: =IF(Paramètres!$B$20=0,0,B9/(DAY(DATE($B$5,$B$4+1,0))*Paramètres!$B$20)) -> 0.25806452
A11: Annulations | B11: =COUNTIFS(Réservations!$T$4:$T$303,$B$4,Réservations!$U$4:$U$303,$B$5,Réservations!$P$4:$P$303,"Annulée") -> 0
A13: FINANCES
A14: Chiffre d'affaires brut | B14: =SUMIFS(Réservations!$J$4:$J$303,Réservations!$T$4:$T$303,$B$4,Réservations!$U$4:$U$303,$B$5,Réservations!$P$4:$P$303,"<>Annulée") -> 5400
A15: Commissions plateformes | B15: =SUMIFS(Réservations!$L$4:$L$303,Réservations!$T$4:$T$303,$B$4,Réservations!$U$4:$U$303,$B$5,Réservations!$P$4:$P$303,"<>Annulée") -> 498
A16: Revenus MG Hôte (frais de conciergerie) | B16: =SUMIFS(Réservations!$N$4:$N$303,Réservations!$T$4:$T$303,$B$4,Réservations!$U$4:$U$303,$B$5,Réservations!$P$4:$P$303,"<>Annulée") -> 980.4
A17: Net versé aux propriétaires | B17: =SUMIFS(Réservations!$O$4:$O$303,Réservations!$T$4:$T$303,$B$4,Réservations!$U$4:$U$303,$B$5,Réservations!$P$4:$P$303,"<>Annulée") -> 3921.6
A18: Total dépenses | B18: =SUMIFS(Dépenses!$E$4:$E$303,Dépenses!$F$4:$F$303,$B$4,Dépenses!$G$4:$G$303,$B$5) -> 530
A19: Résultat MG Hôte (revenus − dépenses) | B19: =B16-B18 -> 450.4
A21: OPÉRATIONNEL
A22: Ménages faits ce mois | B22: =COUNTIFS(Ménage!$D$4:$D$203,"Fait",Ménage!$A$4:$A$203,">="&DATE($B$5,$B$4,1),Ménage!$A$4:$A$203,"<"&DATE($B$5,$B$4+1,1)) -> 1
A23: Ménages en attente ce mois | B23: =COUNTIFS(Ménage!$D$4:$D$203,"En attente",Ménage!$A$4:$A$203,">="&DATE($B$5,$B$4,1),Ménage!$A$4:$A$203,"<"&DATE($B$5,$B$4+1,1)) -> 1
A24: Incidents ouverts / en cours | B24: =COUNTIF(Incidents!$E$4:$E$103,"Ouvert")+COUNTIF(Incidents!$E$4:$E$103,"En cours") -> 1
A25: Incidents résolus ce mois | B25: =COUNTIFS(Incidents!$E$4:$E$103,"Résolu",Incidents!$G$4:$G$103,">="&DATE($B$5,$B$4,1),Incidents!$G$4:$G$103,"<"&DATE($B$5,$B$4+1,1)) -> 0

Sheet Paramètres
A1: PARAMÈTRES — MG HÔTE
A2: MG Hôte — Conciergerie · Location courte durée
A4: Année de suivi (Synthèse) | B4: 2026
A5: Devise | B5: MAD
A7: LISTE DES BIENS | D7: COMMISSIONS PLATEFORMES | G7: LISTES DE VALIDATION
A8: Bien | B8: Actif (Oui/Non) | D8: Plateforme | E8: % commission | G8: Statut résa | H8: Payé | I8: Ménage | J8: Catégorie dépense | K8: Priorité | L8: Statut incident
A9: Bien 1 | B9: Oui | D9: Airbnb | E9: 0.03 | G9: Confirmée | H9: Oui | I9: Fait | J9: Maintenance | K9: Haute | L9: Ouvert
A10: Bien 2 | B10: Non | D10: Booking | E10: 0.15 | G10: Terminée | H10: Non | I10: En attente | J10: Consommables | K10: Moyenne | L10: En cours
A11: Bien 3 | B11: Non | D11: Directe | E11: 0 | G11: Annulée | J11: Électricité | K11: Basse | L11: Résolu
A12: Bien 4 | B12: Non | J12: Eau
A13: Bien 5 | B13: Non | J13: Publicité
A14: Bien 6 | B14: Non | J14: Autre
A15: Bien 7 | B15: Non
A16: Bien 8 | B16: Non
A17: Bien 9 | B17: Non
A18: Bien 10 | B18: Non
A20: Nombre de biens actifs | B20: =COUNTIF(B9:B18,"Oui") -> 1
A22: SEUILS D'ALERTE
A23: Logement vide au-delà de (jours) | B23: 14
A24: Résultat mensuel minimum (MAD) | B24: 1000

Sheet Mode d'emploi
A1: MODE D'EMPLOI & AUTOMATISATIONS
A2: MG Hôte — Conciergerie · Location courte durée
A5: LÉGENDE DES COULEURS
A6: • Cellules à fond doré clair + texte bleu = zones de SAISIE (modifiables).
A7: • Cellules blanches à texte noir = FORMULES automatiques (ne pas modifier).
A8: • Les onglets sont protégés SANS mot de passe : Révision > Ôter la protection de la feuille si besoin.
A9: • Les lignes d'exemple (marquées « exemple ») sont à remplacer par vos vraies données.
A11: UTILISATION QUOTIDIENNE
A12: 1. Nouvelle réservation : onglet Réservations, remplir une ligne (ID, Bien, Plateforme, Client, dates, prix/nuit, statut, payé).
A13: Les nuits, commissions, frais MG Hôte et net propriétaire se calculent automatiquement.
A14: 2. Annulation : passer le Statut à « Annulée » — la ligne est barrée en rouge et exclue de tous les calculs.
A15: 3. Dépenses / Ménage / Incidents : une ligne par événement dans l'onglet correspondant.
... A65: Pour insérer votre logo : onglet Accueil (ou Facture) > Insertion > Images > choisir votre fichier logo, puis le placer en haut à droite.
