Workbook
Name Seuil_Rentabilite: Paramètres!$D$16
Name Seuil_Vide: Paramètres!$D$17
Name Commission_Defaut: Paramètres!$D$18

Sheet Accueil
A1: MG HÔTE
A6: Conciergerie Airbnb & Booking — Villas, Appartements, Riads
A7: Note : insérez votre logo officiel ici (Insertion > Images) à la place de ce bandeau texte — les couleurs noir/or du classeur sont déjà calées sur votre charte.
A9: Sommaire du classeur
B11: Tableau de bord | C11: Vue d'ensemble : arrivées du jour, occupation, finances, alertes, évolution mensuelle.
B12: Réservations | C12: Journal de toutes les réservations (Airbnb, Booking, directes) et annulations.
B13: Formulaire Réservation | C13: Aide de saisie visuelle pour ajouter une nouvelle réservation.
B14: Biens | C14: Liste des biens gérés (Bien 1, Bien 2…).
B15: Propriétaires | C15: Fiches des propriétaires (contact, RIB, mode de paiement).
B16: Finances | C16: Mini comptabilité mensuelle par bien : revenus, charges, résultat net.
B17: Ménage | C17: Suivi du ménage par réservation : fait / en attente, compte-rendu.
B18: Maintenance | C18: Suivi des incidents et de leur priorité.
B19: Alertes | C19: Paiements en retard, ménages oubliés, rentabilité faible, logements vides.
B20: Facture Propriétaire | C20: Facture imprimable/PDF générée automatiquement par bien et par mois.
B21: Rapport Mensuel | C21: Synthèse mensuelle imprimable/PDF, tous biens confondus.
B22: Paramètres | C22: Listes déroulantes et seuils d'alerte — à ne modifier qu'avec précaution.
A24: Légende des couleurs
B26: Cellule dorée | C26: =zone modifiable (saisie libre).
B27: Cellule blanche | C27: =calcul automatique (formule protégée).
A29: Sécurité & sauvegarde
B31: • Les onglets sont protégés : seules les cellules dorées sont modifiables, les formules sont verrouillées (mot de passe : voir onglet Paramètres).
B32: • Structure du classeur protégée pour éviter la suppression ou le déplacement accidentel d'un onglet.
B33: • Activez l'enregistrement automatique dans Excel : enregistrez le fichier sur OneDrive/SharePoint puis activez « Enregistrement automatique » en haut de la fenêtre Excel.
B34: • Pour retrouver un historique des versions : Fichier > Informations > Historique des versions (nécessite OneDrive/SharePoint).
B35: • Pour un suivi collaboratif des modifications : Révision > Partager le classeur (ou co-édition via OneDrive si vous travaillez à plusieurs).
A37: Export PDF
B39: • Facture Propriétaire et Rapport Mensuel sont préformatés pour l'impression (zone d'impression + mise en page 1 page définies).
B40: • Pour exporter en PDF : ouvrez l'onglet souhaité, puis Fichier > Exporter > Créer un document PDF/XPS (ou Ctrl+P > Imprimante « Microsoft Print to PDF »).

Sheet Tableau de bord
A1: MG HÔTE — TABLEAU DE BORD
A2: ="Données au "&TEXT(TODAY(),"dd/mm/yyyy")
A4: Aujourd'hui
B5: ARRIVÉES AUJOURD'HUI | F5: TAUX D'OCCUPATION (MOIS) | J5: NUITS RÉSERVÉES (MOIS)
B6: =COUNTIFS(T_Reservations[Arrivée],TODAY(),T_Reservations[Statut],"<>Annulée") | F6: =IFERROR(J6/(COUNTIF(T_Biens[Statut],"Actif")*DAY(EOMONTH(TODAY(),0))),0) | J6: =SUMIFS(T_Reservations[Nuits],T_Reservations[Mois],TEXT(TODAY(),"yyyy-mm"),T_Reservations[Statut],"<>Annulée")
A9: Bloc Financier (mois en cours)
B11: Chiffre d'affaires brut du mois | G11: =SUMIFS(T_Reservations[Prix total (TTC)],T_Reservations[Mois],TEXT(TODAY(),"yyyy-mm"),T_Reservations[Statut],"<>Annulée")
B12: Charges du mois | G12: =SUMIFS(T_Finances[Total charges],T_Finances[Mois],TEXT(TODAY(),"yyyy-mm"))
B13: Résultat net du mois | G13: =SUMIFS(T_Finances[Résultat net propriétaire],T_Finances[Mois],TEXT(TODAY(),"yyyy-mm"))
B14: Impayés en cours (tous biens) | G14: =SUMIFS(T_Reservations[Solde dû],T_Reservations[Soldé],"Non")
B15: Résultat net cumulé (année) | G15: =SUMIFS(T_Finances[Résultat net propriétaire],T_Finances[Mois],TEXT(TODAY(),"yyyy")&"*")
A17: Bloc Opérationnel — Alertes
B19: PAIEMENTS EN RETARD | F19: MÉNAGES OUBLIÉS | J19: RENTABILITÉ FAIBLE | N19: LOGEMENTS VIDES
B20: ='Alertes'!B6 | F20: ='Alertes'!F6 | J20: ='Alertes'!J6 | N20: ='Alertes'!N6
A23: Bloc Performance — Évolution mensuelle (CA & taux d'occupation)
A44: Données du graphique — ne pas supprimer (12 derniers mois)
B45: Mois | C45: Chiffre d'affaires | D45: Taux d'occupation
B46: =EOMONTH(TODAY(),-11-1)+1 | C46: =SUMIFS(T_Reservations[Prix total (TTC)],T_Reservations[Mois],TEXT(B46,"yyyy-mm"),T_Reservations[Statut],"<>Annulée") | D46: =IFERROR(SUMIFS(T_Reservations[Nuits],T_Reservations[Mois],TEXT(B46,"yyyy-mm"),T_Reservations[Statut],"<>Annulée")/(COUNTIF(T_Biens[Statut],"Actif")*DAY(EOMONTH(B46,0))),0)
B47: =EOMONTH(TODAY(),-10-1)+1 | C47: =SUMIFS(T_Reservations[Prix total (TTC)],T_Reservations[Mois],TEXT(B47,"yyyy-mm"),T_Reservations[Statut],"<>Annulée") | D47: =IFERROR(SUMIFS(T_Reservations[Nuits],T_Reservations[Mois],TEXT(B47,"yyyy-mm"),T_Reservations[Statut],"<>Annulée")/(COUNTIF(T_Biens[Statut],"Actif")*DAY(EOMONTH(B47,0))),0)
B48: =EOMONTH(TODAY(),-9-1)+1 | C48: =SUMIFS(T_Reservations[Prix total (TTC)],T_Reservations[Mois],TEXT(B48,"yyyy-mm"),T_Reservations[Statut],"<>Annulée") | D48: =IFERROR(SUMIFS(T_Reservations[Nuits],T_Reservations[Mois],TEXT(B48,"yyyy-mm"),T_Reservations[Statut],"<>Annulée")/(COUNTIF(T_Biens[Statut],"Actif")*DAY(EOMONTH(B48,0))),0)
B49: =EOMONTH(TODAY(),-8-1)+1 | C49: =SUMIFS(T_Reservations[Prix total (TTC)],T_Reservations[Mois],TEXT(B49,"yyyy-mm"),T_Reservations[Statut],"<>Annulée") | D49: =IFERROR(SUMIFS(T_Reservations[Nuits],T_Reservations[Mois],TEXT(B49,"yyyy-mm"),T_Reservations[Statut],"<>Annulée")/(COUNTIF(T_Biens[Statut],"Actif")*DAY(EOMONTH(B49,0))),0)
B50: =EOMONTH(TODAY(),-7-1)+1 | C50: =SUMIFS(T_Reservations[Prix total (TTC)],T_Reservations[Mois],TEXT(B50,"yyyy-mm"),T_Reservations[Statut],"<>Annulée") | D50: =IFERROR(SUMIFS(T_Reservations[Nuits],T_Reservations[Mois],TEXT(B50,"yyyy-mm"),T_Reservations[Statut],"<>Annulée")/(COUNTIF(T_Biens[Statut],"Actif")*DAY(EOMONTH(B50,0))),0)
B51: =EOMONTH(TODAY(),-6-1)+1 | C51: =SUMIFS(T_Reservations[Prix total (TTC)],T_Reservations[Mois],TEXT(B51,"yyyy-mm"),T_Reservations[Statut],"<>Annulée") | D51: =IFERROR(SUMIFS(T_Reservations[Nuits],T_Reservations[Mois],TEXT(B51,"yyyy-mm"),T_Reservations[Statut],"<>Annulée")/(COUNTIF(T_Biens[Statut],"Actif")*DAY(EOMONTH(B51,0))),0)
B52: =EOMONTH(TODAY(),-5-1)+1 | C52: =SUMIFS(T_Reservations[Prix total (TTC)],T_Reservations[Mois],TEXT(B52,"yyyy-mm"),T_Reservations[Statut],"<>Annulée") | D52: =IFERROR(SUMIFS(T_Reservations[Nuits],T_Reservations[Mois],TEXT(B52,"yyyy-mm"),T_Reservations[Statut],"<>Annulée")/(COUNTIF(T_Biens[Statut],"Actif")*DAY(EOMONTH(B52,0))),0)
B53: =EOMONTH(TODAY(),-4-1)+1 | C53: =SUMIFS(T_Reservations[Prix total (TTC)],T_Reservations[Mois],TEXT(B53,"yyyy-mm"),T_Reservations[Statut],"<>Annulée") | D53: =IFERROR(SUMIFS(T_Reservations[Nuits],T_Reservations[Mois],TEXT(B53,"yyyy-mm"),T_Reservations[Statut],"<>Annulée")/(COUNTIF(T_Biens[Statut],"Actif")*DAY(EOMONTH(B53,0))),0)
B54: =EOMONTH(TODAY(),-3-1)+1 | C54: =SUMIFS(T_Reservations[Prix total (TTC)],T_Reservations[Mois],TEXT(B54,"yyyy-mm"),T_Reservations[Statut],"<>Annulée") | D54: =IFERROR(SUMIFS(T_Reservations[Nuits],T_Reservations[Mois],TEXT(B54,"yyyy-mm"),T_Reservations[Statut],"<>Annulée")/(COUNTIF(T_Biens[Statut],"Actif")*DAY(EOMONTH(B54,0))),0)
B55: =EOMONTH(TODAY(),-2-1)+1 | C55: =SUMIFS(T_Reservations[Prix total (TTC)],T_Reservations[Mois],TEXT(B55,"yyyy-mm"),T_Reservations[Statut],"<>Annulée") | D55: =IFERROR(SUMIFS(T_Reservations[Nuits],T_Reservations[Mois],TEXT(B55,"yyyy-mm"),T_Reservations[Statut],"<>Annulée")/(COUNTIF(T_Biens[Statut],"Actif")*DAY(EOMONTH(B55,0))),0)
B56: =EOMONTH(TODAY(),-1-1)+1 | C56: =SUMIFS(T_Reservations[Prix total (TTC)],T_Reservations[Mois],TEXT(B56,"yyyy-mm"),T_Reservations[Statut],"<>Annulée") | D56: =IFERROR(SUMIFS(T_Reservations[Nuits],T_Reservations[Mois],TEXT(B56,"yyyy-mm"),T_Reservations[Statut],"<>Annulée")/(COUNTIF(T_Biens[Statut],"Actif")*DAY(EOMONTH(B56,0))),0)
B57: =EOMONTH(TODAY(),-0-1)+1 | C57: =SUMIFS(T_Reservations[Prix total (TTC)],T_Reservations[Mois],TEXT(B57,"yyyy-mm"),T_Reservations[Statut],"<>Annulée") | D57: =IFERROR(SUMIFS(T_Reservations[Nuits],T_Reservations[Mois],TEXT(B57,"yyyy-mm"),T_Reservations[Statut],"<>Annulée")/(COUNTIF(T_Biens[Statut],"Actif")*DAY(EOMONTH(B57,0))),0)
B59: Hypothèse : le taux d'occupation mensuel affiché ici rattache chaque nuit réservée au mois de la date d'arrivée (approximation simple, sans répartition au prorata pour les séjours à cheval sur deux mois).

Sheet Réservations
A1: RÉSERVATIONS — Directes, Airbnb & Booking
A2: Ajoutez une réservation en bas du tableau (utilisez l'onglet 'Formulaire Réservation' comme aide de saisie). Cellules dorées = à saisir.
A4: N° | B4: Bien | C4: Plateforme | D4: Client | E4: Contact client | F4: Arrivée | G4: Départ | H4: Nuits | I4: Voyageurs | J4: Prix total (TTC) | K4: Commission plateforme % | L4: Montant net | M4: Statut | N4: Acompte reçu | O4: Solde dû | P4: Soldé | Q4: Ménage fait | R4: Retard paiement | S4: Mois | T4: Notes
A5: =IF(D5="","",ROW()-4) | B5: Bien 1 | C5: Airbnb | D5: Ex: Jean Dupont | E5: jean.dupont@email.com | F5: 2026-07-10 | G5: 2026-07-15 | H5: =IF(AND(G5<>"",F5<>""),G5-F5,"") | I5: 2 | J5: 5000 | K5: 0.03 | L5: =IF(J5="","",J5*(1-K5)) | M5: Confirmée | N5: 5000 | O5: =IF(J5="","",IF(M5="Annulée",0,J5-N5)) | P5: =IF(J5="","",IF(M5="Annulée","-",IF(O5<=0,"Oui","Non"))) | Q5: Oui | R5: =IF(OR(J5="",G5=""),"",IF(AND(M5<>"Annulée",O5>0,G5<TODAY()),"⚠️ Retard","")) | S5: =IF(F5="","",TEXT(F5,"yyyy-mm"))
A6: =IF(D6="","",ROW()-4) | H6: =IF(AND(G6<>"",F6<>""),G6-F6,"") | L6: =IF(J6="","",J6*(1-K6)) | O6: =IF(J6="","",IF(M6="Annulée",0,J6-N6)) | P6: =IF(J6="","",IF(M6="Annulée","-",IF(O6<=0,"Oui","Non"))) | R6: =IF(OR(J6="",G6=""),"",IF(AND(M6<>"Annulée",O6>0,G6<TODAY()),"⚠️ Retard","")) | S6: =IF(F6="","",TEXT(F6,"yyyy-mm"))
A7: =IF(D7="","",ROW()-4) | H7: =IF(AND(G7<>"",F7<>""),G7-F7,"") | L7: =IF(J7="","",J7*(1-K7)) | O7: =IF(J7="","",IF(M7="Annulée",0,J7-N7)) | P7: =IF(J7="","",IF(M7="Annulée","-",IF(O7<=0,"Oui","Non"))) | R7: =IF(OR(J7="",G7=""),"",IF(AND(M7<>"Annulée",O7>0,G7<TODAY()),"⚠️ Retard","")) | S7: =IF(F7="","",TEXT(F7,"yyyy-mm"))
A8: =IF(D8="","",ROW()-4) | H8: =IF(AND(G8<>"",F8<>""),G8-F8,"") | L8: =IF(J8="","",J8*(1-K8)) | O8: =IF(J8="","",IF(M8="Annulée",0,J8-N8)) | P8: =IF(J8="","",IF(M8="Annulée","-",IF(O8<=0,"Oui","Non"))) | R8: =IF(OR(J8="",G8=""),"",IF(AND(M8<>"Annulée",O8>0,G8<TODAY()),"⚠️ Retard","")) | S8: =IF(F8="","",TEXT(F8,"yyyy-mm"))
A9: =IF(D9="","",ROW()-4) | H9: =IF(AND(G9<>"",F9<>""),G9-F9,"") | L9: =IF(J9="","",J9*(1-K9)) | O9: =IF(J9="","",IF(M9="Annulée",0,J9-N9)) | P9: =IF(J9="","",IF(M9="Annulée","-",IF(O9<=0,"Oui","Non"))) | R9: =IF(OR(J9="",G9=""),"",IF(AND(M9<>"Annulée",O9>0,G9<TODAY()),"⚠️ Retard","")) | S9: =IF(F9="","",TEXT(F9,"yyyy-mm"))
A10: =IF(D10="","",ROW()-4) | H10: =IF(AND(G10<>"",F10<>""),G10-F10,"") | L10: =IF(J10="","",J10*(1-K10)) | O10: =IF(J10="","",IF(M10="Annulée",0,J10-N10)) | P10: =IF(J10="","",IF(M10="Annulée","-",IF(O10<=0,"Oui","Non"))) | R10: =IF(OR(J10="",G10=""),"",IF(AND(M10<>"Annulée",O10>0,G10<TODAY()),"⚠️ Retard","")) | S10: =IF(F10="","",TEXT(F10,"yyyy-mm"))
A11: =IF(D11="","",ROW()-4) | H11: =IF(AND(G11<>"",F11<>""),G11-F11,"") | L11: =IF(J11="","",J11*(1-K11)) | O11: =IF(J11="","",IF(M11="Annulée",0,J11-N11)) | P11: =IF(J11="","",IF(M11="Annulée","-",IF(O11<=0,"Oui","Non"))) | R11: =IF(OR(J11="",G11=""),"",IF(AND(M11<>"Annulée",O11>0,G11<TODAY()),"⚠️ Retard","")) | S11: =IF(F11="","",TEXT(F11,"yyyy-mm"))
A12: =IF(D12="","",ROW()-4) | H12: =IF(AND(G12<>"",F12<>""),G12-F12,"") | L12: =IF(J12="","",J12*(1-K12)) | O12: =IF(J12="","",IF(M12="Annulée",0,J12-N12)) | P12: =IF(J12="","",IF(M12="Annulée","-",IF(O12<=0,"Oui","Non"))) | R12: =IF(OR(J12="",G12=""),"",IF(AND(M12<>"Annulée",O12>0,G12<TODAY()),"⚠️ Retard","")) | S12: =IF(F12="","",TEXT(F12,"yyyy-mm"))
A13: =IF(D13="","",ROW()-4) | H13: =IF(AND(G13<>"",F13<>""),G13-F13,"") | L13: =IF(J13="","",J13*(1-K13)) | O13: =IF(J13="","",IF(M13="Annulée",0,J13-N13)) | P13: =IF(J13="","",IF(M13="Annulée","-",IF(O13<=0,"Oui","Non"))) | R13: =IF(OR(J13="",G13=""),"",IF(AND(M13<>"Annulée",O13>0,G13<TODAY()),"⚠️ Retard","")) | S13: =IF(F13="","",TEXT(F13,"yyyy-mm"))
A14: =IF(D14="","",ROW()-4) | H14: =IF(AND(G14<>"",F14<>""),G14-F14,"") | L14: =IF(J14="","",J14*(1-K14)) | O14: =IF(J14="","",IF(M14="Annulée",0,J14-N14)) | P14: =IF(J14="","",IF(M14="Annulée","-",IF(O14<=0,"Oui","Non"))) | R14: =IF(OR(J14="",G14=""),"",IF(AND(M14<>"Annulée",O14>0,G14<TODAY()),"⚠️ Retard","")) | S14: =IF(F14="","",TEXT(F14,"yyyy-mm"))
A15: =IF(D15="","",ROW()-4) | H15: =IF(AND(G15<>"",F15<>""),G15-F15,"") | L15: =IF(J15="","",J15*(1-K15)) | O15: =IF(J15="","",IF(M15="Annulée",0,J15-N15)) | P15: =IF(J15="","",IF(M15="Annulée","-",IF(O15<=0,"Oui","Non"))) | R15: =IF(OR(J15="",G15=""),"",IF(AND(M15<>"Annulée",O15>0,G15<TODAY()),"⚠️ Retard","")) | S15: =IF(F15="","",TEXT(F15,"yyyy-mm"))
A16: =IF(D16="","",ROW()-4) | H16: =IF(AND(G16<>"",F16<>""),G16-F16,"") | L16: =IF(J16="","",J16*(1-K16)) | O16: =IF(J16="","",IF(M16="Annulée",0,J16-N16)) | P16: =IF(J16="","",IF(M16="Annulée","-",IF(O16<=0,"Oui","Non"))) | R16: =IF(OR(J16="",G16=""),"",IF(AND(M16<>"Annulée",O16>0,G16<TODAY()),"⚠️ Retard","")) | S16: =IF(F16="","",TEXT(F16,"yyyy-mm"))
A17: =IF(D17="","",ROW()-4) | H17: =IF(AND(G17<>"",F17<>""),G17-F17,"") | L17: =IF(J17="","",J17*(1-K17)) | O17: =IF(J17="","",IF(M17="Annulée",0,J17-N17)) | P17: =IF(J17="","",IF(M17="Annulée","-",IF(O17<=0,"Oui","Non"))) | R17: =IF(OR(J17="",G17=""),"",IF(AND(M17<>"Annulée",O17>0,G17<TODAY()),"⚠️ Retard","")) | S17: =IF(F17="","",TEXT(F17,"yyyy-mm"))
... A154: =IF(D154="","",ROW()-4) | H154: =IF(AND(G154<>"",F154<>""),G154-F154,"") | L154: =IF(J154="","",J154*(1-K154)) | O154: =IF(J154="","",IF(M154="Annulée",0,J154-N154)) | P154: =IF(J154="","",IF(M154="Annulée","-",IF(O154<=0,"Oui","Non"))) | R154: =IF(OR(J154="",G154=""),"",IF(AND(M154<>"Annulée",O154>0,G154<TODAY()),"⚠️ Retard","")) | S154: =IF(F154="","",TEXT(F154,"yyyy-mm"))

Sheet Formulaire Réservation
A1: ➕ NOUVELLE RÉSERVATION — Formulaire de saisie
A2: Remplissez les cellules dorées ci-dessous, puis reportez la ligne dans l'onglet 'Réservations' (copier/coller la ligne complétée en bas du tableau).
A4: Bien
A5: Plateforme
A6: Nom du client
A7: Contact client (tél / email)
A8: Date d'arrivée
A9: Date de départ
A10: Nombre de voyageurs
A11: Prix total (TTC)
A12: Commission plateforme (%)
A13: Statut de la réservation
... A17: Calculs automatiques (aperçu avant report)
A18: Nuits | B18: =IF(AND(B9<>"",B8<>""),B9-B8,"")
A19: Montant net (après commission plateforme) | B19: =IF(B11<>"",B11*(1-B12),"")
A20: Solde dû | B20: =IF(AND(B11<>"",B14<>""),B11-B14,"")
A22: Astuce : ce formulaire sert d'aide de saisie visuelle. La méthode la plus rapide au quotidien reste d'ajouter directement une nouvelle ligne dans le tableau de l'onglet 'Réservations' (les listes déroulantes et les formules se recopient automatiquement).

Sheet Biens
A1: BIENS — Propriétés gérées par MG Hôte
A2: Une ligne par bien. Pour ajouter un bien, insérez une ligne dans le tableau (Bien 2, Bien 3…). Cellules dorées = à saisir.
A4: ID Bien | B4: Nom / Désignation | C4: Type | D4: Adresse | E4: Ville | F4: Capacité (pers.) | G4: Nb chambres | H4: Propriétaire | I4: Plateformes actives | J4: Commission MG Hôte | K4: Statut | L4: Notes
A5: Bien 1 | B5: À compléter | C5: Villa | F5: 4 | G5: 2 | H5: À compléter | I5: Airbnb, Booking | J5: =Commission_Defaut | K5: Actif
A6: Bien 2 | J6: =Commission_Defaut | K6: Inactif
A7: Bien 3 | J7: =Commission_Defaut | K7: Inactif
A8: Bien 4 | J8: =Commission_Defaut | K8: Inactif
A9: Bien 5 | J9: =Commission_Defaut | K9: Inactif
A10: Bien 6 | J10: =Commission_Defaut | K10: Inactif
A11: Bien 7 | J11: =Commission_Defaut | K11: Inactif
A12: Bien 8 | J12: =Commission_Defaut | K12: Inactif
A13: Bien 9 | J13: =Commission_Defaut | K13: Inactif
A14: Bien 10 | J14: =Commission_Defaut | K14: Inactif
A15: Bien 11 | J15: =Commission_Defaut | K15: Inactif
A16: Bien 12 | J16: =Commission_Defaut | K16: Inactif
A17: Bien 13 | J17: =Commission_Defaut | K17: Inactif
... A19: Bien 15 | J19: =Commission_Defaut | K19: Inactif

Sheet Propriétaires
A1: PROPRIÉTAIRES — Fiches propriétaires
A2: Une ligne par propriétaire. Ces informations alimentent les fiches et factures imprimables.
A4: ID Propriétaire | B4: Nom complet | C4: Téléphone | D4: Email | E4: Adresse | F4: Bien(s) géré(s) | G4: RIB / IBAN | H4: Mode paiement préféré | I4: Début contrat | J4: Notes
A5: P1 | B5: À compléter | F5: Bien 1 | H5: Virement
A6: P2
A7: P3
A8: P4
A9: P5
A10: P6
A11: P7
A12: P8
A13: P9
A14: P10
A15: P11
A16: P12
A17: P13
... A19: P15

Sheet Finances
A1: FINANCES — Mini comptabilité mensuelle par bien
A2: Une ligne par bien et par mois. Le revenu locatif se calcule automatiquement depuis l'onglet Réservations ; saisissez les charges du mois en jaune.
A4: Mois | B4: Bien | C4: Revenu locatif | D4: Ménage | E4: Consommables | F4: Électricité | G4: Eau | H4: Publicité | I4: Maintenance | J4: Total charges | K4: Commission MG Hôte % | L4: Commission MG Hôte | M4: Résultat net propriétaire | N4: Marge nette | O4: Alerte rentabilité
A5: 2026-07 | B5: Bien 1 | C5: =IF(OR(A5="",B5=""),"",SUMIFS(T_Reservations[Prix total (TTC)],T_Reservations[Bien],B5,T_Reservations[Mois],A5,T_Reservations[Statut],"<>Annulée")) | D5: 400 | E5: 150 | F5: 300 | G5: 100 | H5: 200 | I5: =IF(OR(A5="",B5=""),"",SUMIFS(T_Maintenance[Coût],T_Maintenance[Bien],B5,T_Maintenance[Mois],A5)) | J5: =IF(A5="","",SUM(D5:I5)) | K5: =Commission_Defaut | L5: =IF(OR(A5="",K5=""),"",C5*K5) | M5: =IF(A5="","",C5-J5-L5) | N5: =IF(A5="","",IFERROR(M5/C5,0)) | O5: =IF(A5="","",IF(N5<Seuil_Rentabilite,"⚠️ Faible","OK"))
C6: =IF(OR(A6="",B6=""),"",SUMIFS(T_Reservations[Prix total (TTC)],T_Reservations[Bien],B6,T_Reservations[Mois],A6,T_Reservations[Statut],"<>Annulée")) | I6: =IF(OR(A6="",B6=""),"",SUMIFS(T_Maintenance[Coût],T_Maintenance[Bien],B6,T_Maintenance[Mois],A6)) | J6: =IF(A6="","",SUM(D6:I6)) | L6: =IF(OR(A6="",K6=""),"",C6*K6) | M6: =IF(A6="","",C6-J6-L6) | N6: =IF(A6="","",IFERROR(M6/C6,0)) | O6: =IF(A6="","",IF(N6<Seuil_Rentabilite,"⚠️ Faible","OK"))
C7: =IF(OR(A7="",B7=""),"",SUMIFS(T_Reservations[Prix total (TTC)],T_Reservations[Bien],B7,T_Reservations[Mois],A7,T_Reservations[Statut],"<>Annulée")) | I7: =IF(OR(A7="",B7=""),"",SUMIFS(T_Maintenance[Coût],T_Maintenance[Bien],B7,T_Maintenance[Mois],A7)) | J7: =IF(A7="","",SUM(D7:I7)) | L7: =IF(OR(A7="",K7=""),"",C7*K7) | M7: =IF(A7="","",C7-J7-L7) | N7: =IF(A7="","",IFERROR(M7/C7,0)) | O7: =IF(A7="","",IF(N7<Seuil_Rentabilite,"⚠️ Faible","OK"))
C8: =IF(OR(A8="",B8=""),"",SUMIFS(T_Reservations[Prix total (TTC)],T_Reservations[Bien],B8,T_Reservations[Mois],A8,T_Reservations[Statut],"<>Annulée")) | I8: =IF(OR(A8="",B8=""),"",SUMIFS(T_Maintenance[Coût],T_Maintenance[Bien],B8,T_Maintenance[Mois],A8)) | J8: =IF(A8="","",SUM(D8:I8)) | L8: =IF(OR(A8="",K8=""),"",C8*K8) | M8: =IF(A8="","",C8-J8-L8) | N8: =IF(A8="","",IFERROR(M8/C8,0)) | O8: =IF(A8="","",IF(N8<Seuil_Rentabilite,"⚠️ Faible","OK"))
C9: =IF(OR(A9="",B9=""),"",SUMIFS(T_Reservations[Prix total (TTC)],T_Reservations[Bien],B9,T_Reservations[Mois],A9,T_Reservations[Statut],"<>Annulée")) | I9: =IF(OR(A9="",B9=""),"",SUMIFS(T_Maintenance[Coût],T_Maintenance[Bien],B9,T_Maintenance[Mois],A9)) | J9: =IF(A9="","",SUM(D9:I9)) | L9: =IF(OR(A9="",K9=""),"",C9*K9) | M9: =IF(A9="","",C9-J9-L9) | N9: =IF(A9="","",IFERROR(M9/C9,0)) | O9: =IF(A9="","",IF(N9<Seuil_Rentabilite,"⚠️ Faible","OK"))
C10: =IF(OR(A10="",B10=""),"",SUMIFS(T_Reservations[Prix total (TTC)],T_Reservations[Bien],B10,T_Reservations[Mois],A10,T_Reservations[Statut],"<>Annulée")) | I10: =IF(OR(A10="",B10=""),"",SUMIFS(T_Maintenance[Coût],T_Maintenance[Bien],B10,T_Maintenance[Mois],A10)) | J10: =IF(A10="","",SUM(D10:I10)) | L10: =IF(OR(A10="",K10=""),"",C10*K10) | M10: =IF(A10="","",C10-J10-L10) | N10: =IF(A10="","",IFERROR(M10/C10,0)) | O10: =IF(A10="","",IF(N10<Seuil_Rentabilite,"⚠️ Faible","OK"))
C11: =IF(OR(A11="",B11=""),"",SUMIFS(T_Reservations[Prix total (TTC)],T_Reservations[Bien],B11,T_Reservations[Mois],A11,T_Reservations[Statut],"<>Annulée")) | I11: =IF(OR(A11="",B11=""),"",SUMIFS(T_Maintenance[Coût],T_Maintenance[Bien],B11,T_Maintenance[Mois],A11)) | J11: =IF(A11="","",SUM(D11:I11)) | L11: =IF(OR(A11="",K11=""),"",C11*K11) | M11: =IF(A11="","",C11-J11-L11) | N11: =IF(A11="","",IFERROR(M11/C11,0)) | O11: =IF(A11="","",IF(N11<Seuil_Rentabilite,"⚠️ Faible","OK"))
C12: =IF(OR(A12="",B12=""),"",SUMIFS(T_Reservations[Prix total (TTC)],T_Reservations[Bien],B12,T_Reservations[Mois],A12,T_Reservations[Statut],"<>Annulée")) | I12: =IF(OR(A12="",B12=""),"",SUMIFS(T_Maintenance[Coût],T_Maintenance[Bien],B12,T_Maintenance[Mois],A12)) | J12: =IF(A12="","",SUM(D12:I12)) | L12: =IF(OR(A12="",K12=""),"",C12*K12) | M12: =IF(A12="","",C12-J12-L12) | N12: =IF(A12="","",IFERROR(M12/C12,0)) | O12: =IF(A12="","",IF(N12<Seuil_Rentabilite,"⚠️ Faible","OK"))
C13: =IF(OR(A13="",B13=""),"",SUMIFS(T_Reservations[Prix total (TTC)],T_Reservations[Bien],B13,T_Reservations[Mois],A13,T_Reservations[Statut],"<>Annulée")) | I13: =IF(OR(A13="",B13=""),"",SUMIFS(T_Maintenance[Coût],T_Maintenance[Bien],B13,T_Maintenance[Mois],A13)) | J13: =IF(A13="","",SUM(D13:I13)) | L13: =IF(OR(A13="",K13=""),"",C13*K13) | M13: =IF(A13="","",C13-J13-L13) | N13: =IF(A13="","",IFERROR(M13/C13,0)) | O13: =IF(A13="","",IF(N13<Seuil_Rentabilite,"⚠️ Faible","OK"))
C14: =IF(OR(A14="",B14=""),"",SUMIFS(T_Reservations[Prix total (TTC)],T_Reservations[Bien],B14,T_Reservations[Mois],A14,T_Reservations[Statut],"<>Annulée")) | I14: =IF(OR(A14="",B14=""),"",SUMIFS(T_Maintenance[Coût],T_Maintenance[Bien],B14,T_Maintenance[Mois],A14)) | J14: =IF(A14="","",SUM(D14:I14)) | L14: =IF(OR(A14="",K14=""),"",C14*K14) | M14: =IF(A14="","",C14-J14-L14) | N14: =IF(A14="","",IFERROR(M14/C14,0)) | O14: =IF(A14="","",IF(N14<Seuil_Rentabilite,"⚠️ Faible","OK"))
C15: =IF(OR(A15="",B15=""),"",SUMIFS(T_Reservations[Prix total (TTC)],T_Reservations[Bien],B15,T_Reservations[Mois],A15,T_Reservations[Statut],"<>Annulée")) | I15: =IF(OR(A15="",B15=""),"",SUMIFS(T_Maintenance[Coût],T_Maintenance[Bien],B15,T_Maintenance[Mois],A15)) | J15: =IF(A15="","",SUM(D15:I15)) | L15: =IF(OR(A15="",K15=""),"",C15*K15) | M15: =IF(A15="","",C15-J15-L15) | N15: =IF(A15="","",IFERROR(M15/C15,0)) | O15: =IF(A15="","",IF(N15<Seuil_Rentabilite,"⚠️ Faible","OK"))
C16: =IF(OR(A16="",B16=""),"",SUMIFS(T_Reservations[Prix total (TTC)],T_Reservations[Bien],B16,T_Reservations[Mois],A16,T_Reservations[Statut],"<>Annulée")) | I16: =IF(OR(A16="",B16=""),"",SUMIFS(T_Maintenance[Coût],T_Maintenance[Bien],B16,T_Maintenance[Mois],A16)) | J16: =IF(A16="","",SUM(D16:I16)) | L16: =IF(OR(A16="",K16=""),"",C16*K16) | M16: =IF(A16="","",C16-J16-L16) | N16: =IF(A16="","",IFERROR(M16/C16,0)) | O16: =IF(A16="","",IF(N16<Seuil_Rentabilite,"⚠️ Faible","OK"))
C17: =IF(OR(A17="",B17=""),"",SUMIFS(T_Reservations[Prix total (TTC)],T_Reservations[Bien],B17,T_Reservations[Mois],A17,T_Reservations[Statut],"<>Annulée")) | I17: =IF(OR(A17="",B17=""),"",SUMIFS(T_Maintenance[Coût],T_Maintenance[Bien],B17,T_Maintenance[Mois],A17)) | J17: =IF(A17="","",SUM(D17:I17)) | L17: =IF(OR(A17="",K17=""),"",C17*K17) | M17: =IF(A17="","",C17-J17-L17) | N17: =IF(A17="","",IFERROR(M17/C17,0)) | O17: =IF(A17="","",IF(N17<Seuil_Rentabilite,"⚠️ Faible","OK"))
... C64: =IF(OR(A64="",B64=""),"",SUMIFS(T_Reservations[Prix total (TTC)],T_Reservations[Bien],B64,T_Reservations[Mois],A64,T_Reservations[Statut],"<>Annulée")) | I64: =IF(OR(A64="",B64=""),"",SUMIFS(T_Maintenance[Coût],T_Maintenance[Bien],B64,T_Maintenance[Mois],A64)) | J64: =IF(A64="","",SUM(D64:I64)) | L64: =IF(OR(A64="",K64=""),"",C64*K64) | M64: =IF(A64="","",C64-J64-L64) | N64: =IF(A64="","",IFERROR(M64/C64,0)) | O64: =IF(A64="","",IF(N64<Seuil_Rentabilite,"⚠️ Faible","OK"))

Sheet Ménage
A1: MÉNAGE — Suivi par réservation
A2: Une ligne par passage de ménage. Le statut 'En attente' avec une date passée déclenche une alerte automatique.
A4: Date | B4: Bien | C4: Réservation liée (N°) | D4: Statut | E4: Compte-rendu | F4: Responsable | G4: Alerte
A5: 2026-07-15 | B5: Bien 1 | C5: 1 | D5: Fait | E5: RAS, logement en bon état | F5: Ex: Fatima | G5: =IF(A5="","",IF(AND(D5="En attente",A5<TODAY()),"⚠️ En retard",""))
G6: =IF(A6="","",IF(AND(D6="En attente",A6<TODAY()),"⚠️ En retard",""))
G7: =IF(A7="","",IF(AND(D7="En attente",A7<TODAY()),"⚠️ En retard",""))
G8: =IF(A8="","",IF(AND(D8="En attente",A8<TODAY()),"⚠️ En retard",""))
G9: =IF(A9="","",IF(AND(D9="En attente",A9<TODAY()),"⚠️ En retard",""))
G10: =IF(A10="","",IF(AND(D10="En attente",A10<TODAY()),"⚠️ En retard",""))
G11: =IF(A11="","",IF(AND(D11="En attente",A11<TODAY()),"⚠️ En retard",""))
G12: =IF(A12="","",IF(AND(D12="En attente",A12<TODAY()),"⚠️ En retard",""))
G13: =IF(A13="","",IF(AND(D13="En attente",A13<TODAY()),"⚠️ En retard",""))
G14: =IF(A14="","",IF(AND(D14="En attente",A14<TODAY()),"⚠️ En retard",""))
G15: =IF(A15="","",IF(AND(D15="En attente",A15<TODAY()),"⚠️ En retard",""))
G16: =IF(A16="","",IF(AND(D16="En attente",A16<TODAY()),"⚠️ En retard",""))
G17: =IF(A17="","",IF(AND(D17="En attente",A17<TODAY()),"⚠️ En retard",""))
... G154: =IF(A154="","",IF(AND(D154="En attente",A154<TODAY()),"⚠️ En retard",""))

Sheet Maintenance
A1: MAINTENANCE — Suivi des incidents
A2: Une ligne par incident signalé. Priorisez selon l'urgence pour le confort du voyageur.
A4: Date signalement | B4: Bien | C4: Description incident | D4: Priorité | E4: Statut | F4: Coût | G4: Date résolution | H4: Notes | I4: Mois
A5: 2026-07-05 | B5: Bien 1 | C5: Ex: Climatiseur en panne | D5: Haute | E5: Résolu | F5: 350 | G5: 2026-07-06 | I5: =IF(A5="","",TEXT(A5,"yyyy-mm"))
I6: =IF(A6="","",TEXT(A6,"yyyy-mm"))
I7: =IF(A7="","",TEXT(A7,"yyyy-mm"))
I8: =IF(A8="","",TEXT(A8,"yyyy-mm"))
I9: =IF(A9="","",TEXT(A9,"yyyy-mm"))
I10: =IF(A10="","",TEXT(A10,"yyyy-mm"))
I11: =IF(A11="","",TEXT(A11,"yyyy-mm"))
I12: =IF(A12="","",TEXT(A12,"yyyy-mm"))
I13: =IF(A13="","",TEXT(A13,"yyyy-mm"))
I14: =IF(A14="","",TEXT(A14,"yyyy-mm"))
I15: =IF(A15="","",TEXT(A15,"yyyy-mm"))
I16: =IF(A16="","",TEXT(A16,"yyyy-mm"))
I17: =IF(A17="","",TEXT(A17,"yyyy-mm"))
... I64: =IF(A64="","",TEXT(A64,"yyyy-mm"))

Sheet Alertes
A1: ALERTES — Ce qui mérite votre attention aujourd'hui
A2: Ces compteurs se mettent à jour automatiquement. Filtrez les colonnes correspondantes dans chaque onglet pour voir le détail.
B5: PAIEMENTS EN RETARD | F5: MÉNAGES OUBLIÉS | J5: RENTABILITÉ FAIBLE (MOIS EN COURS) | N5: LOGEMENTS VIDES > SEUIL
B6: =COUNTIF(T_Reservations[Retard paiement],"⚠️ Retard") | F6: =COUNTIF(T_Menage[Alerte],"⚠️ En retard") | J6: =COUNTIFS(T_Finances[Mois],TEXT(TODAY(),"yyyy-mm"),T_Finances[Alerte rentabilité],"⚠️ Faible") | N6: =COUNTIF($E$14:$E$23,"⚠️ Vide trop longtemps")
A11: Détail — Logements vides depuis trop longtemps (vs seuil défini dans Paramètres)
B13: Bien | C13: Dernier départ | D13: Jours sans réservation | E13: Alerte
B14: =IF(Biens!A5="","",Biens!A5) | C14: =IF(B14="","",IF(COUNTIFS(T_Reservations[Bien],B14,T_Reservations[Statut],"<>Annulée")=0,"",_xlfn.MAXIFS(T_Reservations[Départ],T_Reservations[Bien],B14,T_Reservations[Statut],"<>Annulée"))) | D14: =IF(OR(B14="",C14=""),"",TODAY()-C14) | E14: =IF(D14="","",IF(D14>Seuil_Vide,"⚠️ Vide trop longtemps",""))
B15: =IF(Biens!A6="","",Biens!A6) | C15: =IF(B15="","",IF(COUNTIFS(T_Reservations[Bien],B15,T_Reservations[Statut],"<>Annulée")=0,"",_xlfn.MAXIFS(T_Reservations[Départ],T_Reservations[Bien],B15,T_Reservations[Statut],"<>Annulée"))) | D15: =IF(OR(B15="",C15=""),"",TODAY()-C15) | E15: =IF(D15="","",IF(D15>Seuil_Vide,"⚠️ Vide trop longtemps",""))
B16: =IF(Biens!A7="","",Biens!A7) | C16: =IF(B16="","",IF(COUNTIFS(T_Reservations[Bien],B16,T_Reservations[Statut],"<>Annulée")=0,"",_xlfn.MAXIFS(T_Reservations[Départ],T_Reservations[Bien],B16,T_Reservations[Statut],"<>Annulée"))) | D16: =IF(OR(B16="",C16=""),"",TODAY()-C16) | E16: =IF(D16="","",IF(D16>Seuil_Vide,"⚠️ Vide trop longtemps",""))
B17: =IF(Biens!A8="","",Biens!A8) | C17: =IF(B17="","",IF(COUNTIFS(T_Reservations[Bien],B17,T_Reservations[Statut],"<>Annulée")=0,"",_xlfn.MAXIFS(T_Reservations[Départ],T_Reservations[Bien],B17,T_Reservations[Statut],"<>Annulée"))) | D17: =IF(OR(B17="",C17=""),"",TODAY()-C17) | E17: =IF(D17="","",IF(D17>Seuil_Vide,"⚠️ Vide trop longtemps",""))
B18: =IF(Biens!A9="","",Biens!A9) | C18: =IF(B18="","",IF(COUNTIFS(T_Reservations[Bien],B18,T_Reservations[Statut],"<>Annulée")=0,"",_xlfn.MAXIFS(T_Reservations[Départ],T_Reservations[Bien],B18,T_Reservations[Statut],"<>Annulée"))) | D18: =IF(OR(B18="",C18=""),"",TODAY()-C18) | E18: =IF(D18="","",IF(D18>Seuil_Vide,"⚠️ Vide trop longtemps",""))
B19: =IF(Biens!A10="","",Biens!A10) | C19: =IF(B19="","",IF(COUNTIFS(T_Reservations[Bien],B19,T_Reservations[Statut],"<>Annulée")=0,"",_xlfn.MAXIFS(T_Reservations[Départ],T_Reservations[Bien],B19,T_Reservations[Statut],"<>Annulée"))) | D19: =IF(OR(B19="",C19=""),"",TODAY()-C19) | E19: =IF(D19="","",IF(D19>Seuil_Vide,"⚠️ Vide trop longtemps",""))
B20: =IF(Biens!A11="","",Biens!A11) | C20: =IF(B20="","",IF(COUNTIFS(T_Reservations[Bien],B20,T_Reservations[Statut],"<>Annulée")=0,"",_xlfn.MAXIFS(T_Reservations[Départ],T_Reservations[Bien],B20,T_Reservations[Statut],"<>Annulée"))) | D20: =IF(OR(B20="",C20=""),"",TODAY()-C20) | E20: =IF(D20="","",IF(D20>Seuil_Vide,"⚠️ Vide trop longtemps",""))
B21: =IF(Biens!A12="","",Biens!A12) | C21: =IF(B21="","",IF(COUNTIFS(T_Reservations[Bien],B21,T_Reservations[Statut],"<>Annulée")=0,"",_xlfn.MAXIFS(T_Reservations[Départ],T_Reservations[Bien],B21,T_Reservations[Statut],"<>Annulée"))) | D21: =IF(OR(B21="",C21=""),"",TODAY()-C21) | E21: =IF(D21="","",IF(D21>Seuil_Vide,"⚠️ Vide trop longtemps",""))
B22: =IF(Biens!A13="","",Biens!A13) | C22: =IF(B22="","",IF(COUNTIFS(T_Reservations[Bien],B22,T_Reservations[Statut],"<>Annulée")=0,"",_xlfn.MAXIFS(T_Reservations[Départ],T_Reservations[Bien],B22,T_Reservations[Statut],"<>Annulée"))) | D22: =IF(OR(B22="",C22=""),"",TODAY()-C22) | E22: =IF(D22="","",IF(D22>Seuil_Vide,"⚠️ Vide trop longtemps",""))
B23: =IF(Biens!A14="","",Biens!A14) | C23: =IF(B23="","",IF(COUNTIFS(T_Reservations[Bien],B23,T_Reservations[Statut],"<>Annulée")=0,"",_xlfn.MAXIFS(T_Reservations[Départ],T_Reservations[Bien],B23,T_Reservations[Statut],"<>Annulée"))) | D23: =IF(OR(B23="",C23=""),"",TODAY()-C23) | E23: =IF(D23="","",IF(D23>Seuil_Vide,"⚠️ Vide trop longtemps",""))

Sheet Facture Propriétaire
A1: MG HÔTE — FACTURE PROPRIÉTAIRE
A2: Sélectionnez le bien et le mois : la facture se génère automatiquement depuis l'onglet Finances.
A4: Sélection
B6: Bien | C6: Bien 1 | E6: Mois (aaaa-mm) | F6: 2026-07
B7: N° de facture | C7: ="FACT-"&C6&"-"&F6 | E7: Date d'émission | F7: =TODAY()
A9: Propriétaire
B11: Nom | C11: =IFERROR(INDEX(Biens!$H:$H,MATCH($C$6,Biens!$A:$A,0)),"") | E11: Mode de paiement | F11: =IFERROR(INDEX(Propriétaires!$H:$H,MATCH($C$11,Propriétaires!$B:$B,0)),"Virement")
B12: RIB / IBAN | C12: =IFERROR(INDEX(Propriétaires!$G:$G,MATCH($C$11,Propriétaires!$B:$B,0)),"")
A14: Détail financier du mois
B16: Poste | C16: Montant
B17: Revenu locatif brut | C17: =SUMIFS(T_Reservations[Prix total (TTC)],T_Reservations[Bien],$C$6,T_Reservations[Mois],$F$6,T_Reservations[Statut],"<>Annulée")
B18: Ménage | C18: =-SUMIFS(T_Finances[Ménage],T_Finances[Bien],$C$6,T_Finances[Mois],$F$6)
B19: Consommables | C19: =-SUMIFS(T_Finances[Consommables],T_Finances[Bien],$C$6,T_Finances[Mois],$F$6)
B20: Électricité | C20: =-SUMIFS(T_Finances[Électricité],T_Finances[Bien],$C$6,T_Finances[Mois],$F$6)
B21: Eau | C21: =-SUMIFS(T_Finances[Eau],T_Finances[Bien],$C$6,T_Finances[Mois],$F$6)
B22: Publicité | C22: =-SUMIFS(T_Finances[Publicité],T_Finances[Bien],$C$6,T_Finances[Mois],$F$6)
B23: Maintenance | C23: =-SUMIFS(T_Finances[Maintenance],T_Finances[Bien],$C$6,T_Finances[Mois],$F$6)
B24: Commission MG Hôte | C24: =-SUMIFS(T_Finances[Commission MG Hôte],T_Finances[Bien],$C$6,T_Finances[Mois],$F$6)
B25: NET À VERSER AU PROPRIÉTAIRE | C25: =SUM(C17:C24)
B28: Merci de votre confiance. — MG Hôte, Conciergerie Airbnb & Booking
B31: Signature MG Hôte | E31: Signature Propriétaire

Sheet Rapport Mensuel
A1: MG HÔTE — RAPPORT MENSUEL DE SYNTHÈSE
A2: Sélectionnez le mois : la synthèse se génère automatiquement, tous biens confondus.
B4: Mois (aaaa-mm) | C4: 2026-07 | E4: Date d'édition | F4: =TODAY()
A6: Synthèse financière
B8: Chiffre d'affaires brut total | C8: =SUMIFS(T_Reservations[Prix total (TTC)],T_Reservations[Mois],$C$4,T_Reservations[Statut],"<>Annulée")
B9: Charges totales | C9: =SUMIFS(T_Finances[Total charges],T_Finances[Mois],$C$4)
B10: Commission MG Hôte totale | C10: =SUMIFS(T_Finances[Commission MG Hôte],T_Finances[Mois],$C$4)
B11: Résultat net global (propriétaires) | C11: =SUMIFS(T_Finances[Résultat net propriétaire],T_Finances[Mois],$C$4)
B12: Marge nette moyenne | C12: =IFERROR(C11/C8,0)
A14: Activité réservations
B16: Réservations confirmées / en cours / terminées | C16: =COUNTIFS(T_Reservations[Mois],$C$4,T_Reservations[Statut],"<>Annulée")
B17: Annulations | C17: =COUNTIFS(T_Reservations[Mois],$C$4,T_Reservations[Statut],"Annulée")
B18: Nuits réservées | C18: =SUMIFS(T_Reservations[Nuits],T_Reservations[Mois],$C$4,T_Reservations[Statut],"<>Annulée")
B19: Taux d'occupation moyen | C19: =IFERROR(C18/(COUNTIF(T_Biens[Statut],"Actif")*DAY(EOMONTH(DATEVALUE($C$4&"-01"),0))),0)
A21: Opérationnel
B23: Ménages effectués | C23: =COUNTIFS(T_Menage[Date],">="&DATEVALUE($C$4&"-01"),T_Menage[Date],"<="&EOMONTH(DATEVALUE($C$4&"-01"),0),T_Menage[Statut],"Fait")
B24: Ménages en attente | C24: =COUNTIFS(T_Menage[Date],">="&DATEVALUE($C$4&"-01"),T_Menage[Date],"<="&EOMONTH(DATEVALUE($C$4&"-01"),0),T_Menage[Statut],"En attente")
B25: Incidents maintenance signalés | C25: =COUNTIFS(T_Maintenance[Mois],$C$4)
B26: Incidents maintenance résolus | C26: =COUNTIFS(T_Maintenance[Mois],$C$4,T_Maintenance[Statut],"Résolu")
B29: Rapport généré automatiquement — MG Hôte, Conciergerie Airbnb & Booking

Sheet Paramètres
A1: PARAMÈTRES — Listes de référence & seuils (ne pas supprimer/déplacer les colonnes)
A2: Cet onglet alimente les listes déroulantes de tout le classeur. Vous pouvez modifier les seuils en bas de page.
A4: Listes déroulantes
A6: Plateformes | B6: Statuts réservation | C6: Types de bien | D6: Statuts ménage | E6: Priorités maintenance | F6: Statuts maintenance | G6: Paiement soldé
A7: Airbnb | B7: Confirmée | C7: Villa | D7: Fait | E7: Basse | F7: Signalé | G7: Oui
A8: Booking | B8: En cours | C8: Appartement | D8: En attente | E8: Moyenne | F8: En cours | G8: Non
A9: Direct | B9: Terminée | C9: Riad | E9: Haute | F9: Résolu
B10: Annulée | C10: Autre | E10: Urgente
A14: Seuils d'alerte & paramètres généraux
B16: Seuil rentabilité faible (marge nette) | D16: 0.2
B17: Seuil logement vide (jours sans réservation) | D17: 14
B18: Commission MG Hôte par défaut | D18: 0.2
B19: Mot de passe protection des onglets | D19: MGHote2026
