Workbook
Name Liste_Biens: Biens!$A$5:$A$14
Name Liste_BiensGeneral: Paramètres!$C$3:$C$13
Name Liste_Plateformes: Paramètres!$D$3:$D$5
Name Liste_StatutResa: Paramètres!$E$3:$E$6
Name Liste_TypeBien: Paramètres!$F$3:$F$5
Name Liste_StatutBien: Paramètres!$G$3:$G$4
Name Liste_StatutMenage: Paramètres!$H$3:$H$4
Name Liste_PrioriteMaint: Paramètres!$I$3:$I$6
Name Liste_StatutMaint: Paramètres!$J$3:$J$5
Name Liste_TypeJournal: Paramètres!$K$3:$K$4
Name Liste_CategorieJournal: Paramètres!$L$3:$L$13
Name Liste_ModePaiement: Paramètres!$M$3:$M$7
Name Liste_StatutPaiement: Paramètres!$N$3:$N$5

Sheet Accueil
A1: MG HÔTE | C1: TABLEAU DE BORD
C2: ="MG Hôte — Conciergerie Airbnb & Booking — "&TEXT(TODAY(),"dddd d mmmm yyyy")
A4: INDICATEURS CLÉS — AUJOURD'HUI / CE MOIS-CI
B5: ARRIVÉES AUJOURD'HUI | D5: TAUX D'OCCUPATION (MOIS) | F5: NUITS RÉSERVÉES (MOIS)
B6: =COUNTIFS(Réservations!$G$5:$G$204,TODAY(),Réservations!$Q$5:$Q$204,"<>Annulée") | D6: ='Synthèse Mensuelle'!C16 | F6: ='Synthèse Mensuelle'!B16
A8: BLOC FINANCIER — MOIS EN COURS
B9: CA DU MOIS | D9: DÉPENSES DU MOIS | F9: RÉSULTAT NET | H9: COMMISSION MG HÔTE | J9: DÛ AU PROPRIÉTAIRE
B10: ='Synthèse Mensuelle'!D16 | D10: ='Synthèse Mensuelle'!K16 | F10: ='Synthèse Mensuelle'!L16 | H10: ='Synthèse Mensuelle'!M16 | J10: ='Synthèse Mensuelle'!N16
A12: ALERTES OPÉRATIONNELLES
B13: Indicateur | C13: Valeur | D13: État
B14: Voyageurs non payés (séjour déjà terminé) | C14: =COUNTIFS(Réservations!$R$5:$R$204,"Non payé",Réservations!$H$5:$H$204,"<"&TODAY()) | D14: =IF(C14>0,"À traiter","OK")
B15: Ménages oubliés (en attente, date dépassée) | C15: =COUNTIFS('Ménage'!$D$5:$D$154,"En attente",'Ménage'!$A$5:$A$154,"<"&TODAY()) | D15: =IF(C15>0,"À traiter","OK")
B16: Rentabilité du mois (marge nette) | C16: =IFERROR('Synthèse Mensuelle'!L16/'Synthèse Mensuelle'!D16,0) | D16: =IF('Synthèse Mensuelle'!D16=0,"-",IF(C16<0.2,"Faible","Correcte"))
B17: Logement vide depuis (jours, sans réservation en cours) | C17: =B46 | D17: =IF(C17>=14,"Alerte","OK")
A20: PERFORMANCE — ÉVOLUTION SUR 12 MOIS
A42: Zone de calcul interne (ne pas modifier)
A44: Dernier départ passé (date) | B44: =IFERROR(_xlfn.MAXIFS(Réservations!$H$5:$H$204,Réservations!$H$5:$H$204,"<"&TODAY()),0)
A45: Prochaine arrivée (date) | B45: =IFERROR(_xlfn.MINIFS(Réservations!$G$5:$G$204,Réservations!$G$5:$G$204,">="&TODAY()),0)
A46: Jours sans réservation en cours | B46: =IF(AND(B44>0,TODAY()>B44,OR(B45=0,B45>TODAY())),TODAY()-B44,0)

Sheet Guide
A1: MG HÔTE | C1: GUIDE D'UTILISATION
C2: Fichier de gestion MG Hôte — conciergerie Airbnb, Booking & location courte durée
A4: 1. OBJECTIF DU FICHIER
A5: Ce classeur est l'outil de gestion central de MG Hôte pour le pilotage de la conciergerie (Airbnb, Booking, location courte durée — villas, appartements, riads). Il regroupe la gestion des réservations, des propriétaires, des biens, la comptabilité, le ménage, la maintenance et les documents à imprimer ou exporter en PDF, en vue d'évoluer vers un véritable ERP de conciergerie.
A9: 2. LISTE DES ONGLETS ET LEUR RÔLE
A10: Onglet | C10: Rôle
A11: Accueil | C11: Tableau de bord : indicateurs clés, bloc financier, alertes, graphiques d'évolution.
A12: Réservations | C12: Une ligne = une réservation. Sert aussi de formulaire de saisie.
A13: Biens | C13: Fiche de chaque bien géré (Bien 1, Bien 2...), commission et statut.
A14: Propriétaires | C14: Coordonnées des propriétaires et suivi des versements.
A15: Journal Financier | C15: Mini comptabilité : toutes les recettes et dépenses, une ligne par mouvement.
A16: Synthèse Mensuelle | C16: Agrégats des 12 derniers mois (CA, dépenses, résultat, commission).
A17: Ménage | C17: Statut de ménage (fait / en attente) et compte rendu par passage.
A18: Maintenance | C18: Suivi des incidents, priorité et résolution.
A19: Facture Propriétaire | C19: Fiche propriétaire + décompte financier, prête à imprimer/exporter en PDF.
A20: Rapport Mensuel | C20: Rapport d'activité mensuel complet, prêt à imprimer/exporter en PDF.
A21: Paramètres | C21: Listes utilisées par les menus déroulants (ne pas modifier).
A23: 3. CODE COULEUR
B24: Fond doré clair = zone modifiable (à saisir vous-même)
B25: Fond blanc = calcul automatique (formule protégée, ne pas modifier)
A27: 4. PROTECTION ET MOT DE PASSE
A28: Chaque onglet est protégé : seules les zones dorées sont modifiables, les formules sont verrouillées pour éviter les erreurs de saisie. Mot de passe de protection des feuilles et de la structure du classeur : MGHOTE2026 (Excel > Révision > Protéger la feuille / Protéger le classeur pour le modifier). Conservez ce mot de passe en lieu sûr — changez-le si besoin depuis le même menu.
A32: 5. LOGO MG HÔTE
A33: Un emplacement noir/or réservé au logo figure en haut à gauche de chaque onglet (bloc « MG HÔTE »). Insérez votre logo réel via Excel : Insertion > Images, puis redimensionnez-le sur cet emplacement.
A36: 6. SAUVEGARDE AUTOMATIQUE ET SUIVI DES MODIFICATIONS
A37: AutoSave : enregistrez ce fichier sur OneDrive ou SharePoint (Fichier > Enregistrer une copie > OneDrive), puis activez l'interrupteur AutoSave en haut à gauche d'Excel — vos saisies sont alors sauvegardées en continu. Suivi des modifications / historique : une fois le fichier sur OneDrive, utilisez Fichier > Informations > Historique des versions pour consulter ou restaurer une version antérieure (équivalent moderne du suivi des modifications pour un classeur partagé).
A42: 7. AUTOMATISATIONS — MACROS PDF (Excel Windows uniquement)
A43: Ce fichier .xlsx ne contient pas de macro pré-installée (les macros ne peuvent pas être testées de manière fiable hors d'Excel). Pour activer les boutons PDF en un clic, installez une fois ces 2 macros ci-dessous : 1) Enregistrez le fichier au format .xlsm (Fichier > Enregistrer sous > Classeur Excel (.xlsm)). 2) Ouvrez l'éditeur VBA (Alt+F11) > clic droit sur le nom du classeur > Insérer > Module. 3) Collez le code ci-dessous. 4) Développeur > Insérer > Bouton, puis affectez la macro voulue.
A47: Sub MGHote_GenererFacturePDF() Dim ws As Worksheet, nomFichier As String Set ws = ThisWorkbook.Sheets("Facture Propriétaire") nomFichier = ThisWorkbook.Path & "\Facture_" & Format(Date, "yyyymmdd") & ".pdf" ws.ExportAsFixedFormat Type:=xlTypePDF, Filename:=nomFichier, OpenAfterPublish:=True MsgBox "Facture PDF générée : " & nomFichier, vbInformation, "MG Hôte" End Sub Sub MGHote_GenererRapportPDF() Dim ws As Worksheet, nomFichier As String Set ws = ThisWorkbook.Sheets("Rapport Mensuel") nomFichier = ThisWorkbook.Path & "\Rapport_" & Format(ws.Range("D4").Value, "yyyy-mm") & ".pdf" ws.ExportAsFixedFormat Type:=xlTypePDF, Filename:=nomFichier, OpenAfterPublish:=True MsgBox "Rapport PDF généré : " & nomFichier, vbInformation, "MG Hôte" End Sub Sub MGHote_NouvelleReservation() Dim ws As Worksheet, r As Long Set ws = ThisWorkbook.Sheets("Réservations") ws.Unprotect Password:="MGHOTE2026" r = 5 Do While ws.Cells(r, 2).Value <> "" r = r + 1 Loop ws.Protect Password:="MGHOTE2026", AllowFiltering:=True, AllowSorting:=True ws.Activate ws.Cells(r, 2).Select MsgBox "Nouvelle ligne prête, ligne " & r & ". Saisissez la réservation à partir de la colonne Bien.", vbInformation, "MG Hôte" End Sub
A75: 8. EXPORT PDF SANS MACRO (toujours disponible)
A76: Sans macro, l'export PDF reste simple : ouvrez l'onglet Facture Propriétaire, Rapport Mensuel ou Synthèse Mensuelle (leur zone d'impression est déjà configurée), puis Fichier > Exporter > Créer un PDF/XPS. Le document généré tient sur une page, prêt à envoyer à un propriétaire.

Sheet Réservations
A1: MG HÔTE | C1: RÉSERVATIONS
C2: Saisissez une ligne par réservation — les colonnes grisées se calculent automatiquement
A3: Taux frais plateforme (Airbnb/Booking) | F3: 0.155
A4: ID Résa | B4: Bien | C4: Plateforme | D4: Nom voyageur | E4: Téléphone | F4: Email | G4: Date arrivée | H4: Date départ | I4: Nb nuits | J4: Nb voyageurs | K4: Prix unitaire (MAD) | L4: Prix total (MAD) | M4: Frais plateforme (MAD) | N4: Montant net (MAD) | O4: Commission MG Hôte (MAD) | P4: NET du Proprio (MAD) | Q4: Statut réservation | R4: Statut paiement voyageur | S4: Date de paiement | T4: Notes
I5: =IF(OR($G5="",$H5=""),"",$H5-$G5) | L5: =IF(OR($K5="",$I5=""),"",$K5*$I5) | M5: =IF($L5="","",IF(OR($C5="Airbnb",$C5="Booking"),$L5*$F$3,0)) | N5: =IF($L5="","",$L5-$M5) | O5: =IF($N5="","",$N5*IFERROR(INDEX(Biens!$I$5:$I$14,MATCH($B5,Biens!$A$5:$A$14,0)),0.2)) | P5: =IF($N5="","",$N5-$O5)
I6: =IF(OR($G6="",$H6=""),"",$H6-$G6) | L6: =IF(OR($K6="",$I6=""),"",$K6*$I6) | M6: =IF($L6="","",IF(OR($C6="Airbnb",$C6="Booking"),$L6*$F$3,0)) | N6: =IF($L6="","",$L6-$M6) | O6: =IF($N6="","",$N6*IFERROR(INDEX(Biens!$I$5:$I$14,MATCH($B6,Biens!$A$5:$A$14,0)),0.2)) | P6: =IF($N6="","",$N6-$O6)
I7: =IF(OR($G7="",$H7=""),"",$H7-$G7) | L7: =IF(OR($K7="",$I7=""),"",$K7*$I7) | M7: =IF($L7="","",IF(OR($C7="Airbnb",$C7="Booking"),$L7*$F$3,0)) | N7: =IF($L7="","",$L7-$M7) | O7: =IF($N7="","",$N7*IFERROR(INDEX(Biens!$I$5:$I$14,MATCH($B7,Biens!$A$5:$A$14,0)),0.2)) | P7: =IF($N7="","",$N7-$O7)
I8: =IF(OR($G8="",$H8=""),"",$H8-$G8) | L8: =IF(OR($K8="",$I8=""),"",$K8*$I8) | M8: =IF($L8="","",IF(OR($C8="Airbnb",$C8="Booking"),$L8*$F$3,0)) | N8: =IF($L8="","",$L8-$M8) | O8: =IF($N8="","",$N8*IFERROR(INDEX(Biens!$I$5:$I$14,MATCH($B8,Biens!$A$5:$A$14,0)),0.2)) | P8: =IF($N8="","",$N8-$O8)
I9: =IF(OR($G9="",$H9=""),"",$H9-$G9) | L9: =IF(OR($K9="",$I9=""),"",$K9*$I9) | M9: =IF($L9="","",IF(OR($C9="Airbnb",$C9="Booking"),$L9*$F$3,0)) | N9: =IF($L9="","",$L9-$M9) | O9: =IF($N9="","",$N9*IFERROR(INDEX(Biens!$I$5:$I$14,MATCH($B9,Biens!$A$5:$A$14,0)),0.2)) | P9: =IF($N9="","",$N9-$O9)
I10: =IF(OR($G10="",$H10=""),"",$H10-$G10) | L10: =IF(OR($K10="",$I10=""),"",$K10*$I10) | M10: =IF($L10="","",IF(OR($C10="Airbnb",$C10="Booking"),$L10*$F$3,0)) | N10: =IF($L10="","",$L10-$M10) | O10: =IF($N10="","",$N10*IFERROR(INDEX(Biens!$I$5:$I$14,MATCH($B10,Biens!$A$5:$A$14,0)),0.2)) | P10: =IF($N10="","",$N10-$O10)
I11: =IF(OR($G11="",$H11=""),"",$H11-$G11) | L11: =IF(OR($K11="",$I11=""),"",$K11*$I11) | M11: =IF($L11="","",IF(OR($C11="Airbnb",$C11="Booking"),$L11*$F$3,0)) | N11: =IF($L11="","",$L11-$M11) | O11: =IF($N11="","",$N11*IFERROR(INDEX(Biens!$I$5:$I$14,MATCH($B11,Biens!$A$5:$A$14,0)),0.2)) | P11: =IF($N11="","",$N11-$O11)
I12: =IF(OR($G12="",$H12=""),"",$H12-$G12) | L12: =IF(OR($K12="",$I12=""),"",$K12*$I12) | M12: =IF($L12="","",IF(OR($C12="Airbnb",$C12="Booking"),$L12*$F$3,0)) | N12: =IF($L12="","",$L12-$M12) | O12: =IF($N12="","",$N12*IFERROR(INDEX(Biens!$I$5:$I$14,MATCH($B12,Biens!$A$5:$A$14,0)),0.2)) | P12: =IF($N12="","",$N12-$O12)
I13: =IF(OR($G13="",$H13=""),"",$H13-$G13) | L13: =IF(OR($K13="",$I13=""),"",$K13*$I13) | M13: =IF($L13="","",IF(OR($C13="Airbnb",$C13="Booking"),$L13*$F$3,0)) | N13: =IF($L13="","",$L13-$M13) | O13: =IF($N13="","",$N13*IFERROR(INDEX(Biens!$I$5:$I$14,MATCH($B13,Biens!$A$5:$A$14,0)),0.2)) | P13: =IF($N13="","",$N13-$O13)
I14: =IF(OR($G14="",$H14=""),"",$H14-$G14) | L14: =IF(OR($K14="",$I14=""),"",$K14*$I14) | M14: =IF($L14="","",IF(OR($C14="Airbnb",$C14="Booking"),$L14*$F$3,0)) | N14: =IF($L14="","",$L14-$M14) | O14: =IF($N14="","",$N14*IFERROR(INDEX(Biens!$I$5:$I$14,MATCH($B14,Biens!$A$5:$A$14,0)),0.2)) | P14: =IF($N14="","",$N14-$O14)
I15: =IF(OR($G15="",$H15=""),"",$H15-$G15) | L15: =IF(OR($K15="",$I15=""),"",$K15*$I15) | M15: =IF($L15="","",IF(OR($C15="Airbnb",$C15="Booking"),$L15*$F$3,0)) | N15: =IF($L15="","",$L15-$M15) | O15: =IF($N15="","",$N15*IFERROR(INDEX(Biens!$I$5:$I$14,MATCH($B15,Biens!$A$5:$A$14,0)),0.2)) | P15: =IF($N15="","",$N15-$O15)
I16: =IF(OR($G16="",$H16=""),"",$H16-$G16) | L16: =IF(OR($K16="",$I16=""),"",$K16*$I16) | M16: =IF($L16="","",IF(OR($C16="Airbnb",$C16="Booking"),$L16*$F$3,0)) | N16: =IF($L16="","",$L16-$M16) | O16: =IF($N16="","",$N16*IFERROR(INDEX(Biens!$I$5:$I$14,MATCH($B16,Biens!$A$5:$A$14,0)),0.2)) | P16: =IF($N16="","",$N16-$O16)
... I204: =IF(OR($G204="",$H204=""),"",$H204-$G204) | L204: =IF(OR($K204="",$I204=""),"",$K204*$I204) | M204: =IF($L204="","",IF(OR($C204="Airbnb",$C204="Booking"),$L204*$F$3,0)) | N204: =IF($L204="","",$L204-$M204) | O204: =IF($N204="","",$N204*IFERROR(INDEX(Biens!$I$5:$I$14,MATCH($B204,Biens!$A$5:$A$14,0)),0.2)) | P204: =IF($N204="","",$N204-$O204)

Sheet Biens
A1: MG HÔTE | C1: GESTION DES BIENS
C2: Liste des biens gérés par MG Hôte
A4: Bien | B4: Type | C4: Adresse | D4: Ville | E4: Propriétaire | F4: Capacité (pers.) | G4: Nb chambres | H4: Statut | I4: Commission MG Hôte (%) | J4: Prix moyen nuitée indicatif (MAD) | K4: Date début gestion | L4: Notes
A5: Bien 1 | H5: Actif | I5: 0.2

Sheet Propriétaires
A1: MG HÔTE | C1: GESTION DES PROPRIÉTAIRES
C2: Coordonnées, bien(s) géré(s) et suivi des versements
A4: Nom du propriétaire | B4: Bien(s) géré(s) | C4: Téléphone | D4: Email | E4: Adresse | F4: RIB / IBAN | G4: Mode de paiement | H4: Date dernier versement | I4: Total versé à ce jour (MAD) | J4: Notes
I5: =IF($B5="","",IFERROR(SUMIFS('Journal Financier'!$F$5:$F$304,'Journal Financier'!$B$5:$B$304,$B5,'Journal Financier'!$D$5:$D$304,"Reversement propriétaire"),0))
I6: =IF($B6="","",IFERROR(SUMIFS('Journal Financier'!$F$5:$F$304,'Journal Financier'!$B$5:$B$304,$B6,'Journal Financier'!$D$5:$D$304,"Reversement propriétaire"),0))
I7: =IF($B7="","",IFERROR(SUMIFS('Journal Financier'!$F$5:$F$304,'Journal Financier'!$B$5:$B$304,$B7,'Journal Financier'!$D$5:$D$304,"Reversement propriétaire"),0))
I8: =IF($B8="","",IFERROR(SUMIFS('Journal Financier'!$F$5:$F$304,'Journal Financier'!$B$5:$B$304,$B8,'Journal Financier'!$D$5:$D$304,"Reversement propriétaire"),0))
I9: =IF($B9="","",IFERROR(SUMIFS('Journal Financier'!$F$5:$F$304,'Journal Financier'!$B$5:$B$304,$B9,'Journal Financier'!$D$5:$D$304,"Reversement propriétaire"),0))
I10: =IF($B10="","",IFERROR(SUMIFS('Journal Financier'!$F$5:$F$304,'Journal Financier'!$B$5:$B$304,$B10,'Journal Financier'!$D$5:$D$304,"Reversement propriétaire"),0))
I11: =IF($B11="","",IFERROR(SUMIFS('Journal Financier'!$F$5:$F$304,'Journal Financier'!$B$5:$B$304,$B11,'Journal Financier'!$D$5:$D$304,"Reversement propriétaire"),0))
I12: =IF($B12="","",IFERROR(SUMIFS('Journal Financier'!$F$5:$F$304,'Journal Financier'!$B$5:$B$304,$B12,'Journal Financier'!$D$5:$D$304,"Reversement propriétaire"),0))
I13: =IF($B13="","",IFERROR(SUMIFS('Journal Financier'!$F$5:$F$304,'Journal Financier'!$B$5:$B$304,$B13,'Journal Financier'!$D$5:$D$304,"Reversement propriétaire"),0))
I14: =IF($B14="","",IFERROR(SUMIFS('Journal Financier'!$F$5:$F$304,'Journal Financier'!$B$5:$B$304,$B14,'Journal Financier'!$D$5:$D$304,"Reversement propriétaire"),0))

Sheet Journal Financier
A1: MG HÔTE | C1: JOURNAL FINANCIER
C2: Toutes les recettes et dépenses, une ligne par mouvement
A4: Date | B4: Bien | C4: Type | D4: Catégorie | E4: Description | F4: Montant (MAD) | G4: Montant signé (MAD) | H4: Mode de paiement | I4: Réservation liée | J4: Justificatif / Notes
G5: =IF($F5="","",IF($C5="Recette",$F5,-$F5))
G6: =IF($F6="","",IF($C6="Recette",$F6,-$F6))
G7: =IF($F7="","",IF($C7="Recette",$F7,-$F7))
G8: =IF($F8="","",IF($C8="Recette",$F8,-$F8))
G9: =IF($F9="","",IF($C9="Recette",$F9,-$F9))
G10: =IF($F10="","",IF($C10="Recette",$F10,-$F10))
G11: =IF($F11="","",IF($C11="Recette",$F11,-$F11))
G12: =IF($F12="","",IF($C12="Recette",$F12,-$F12))
G13: =IF($F13="","",IF($C13="Recette",$F13,-$F13))
G14: =IF($F14="","",IF($C14="Recette",$F14,-$F14))
G15: =IF($F15="","",IF($C15="Recette",$F15,-$F15))
G16: =IF($F16="","",IF($C16="Recette",$F16,-$F16))
... G304: =IF($F304="","",IF($C304="Recette",$F304,-$F304))

Sheet Synthèse Mensuelle
A1: MG HÔTE | C1: SYNTHÈSE MENSUELLE
C2: 12 derniers mois — se met à jour automatiquement à l'ouverture du fichier
A3: Taux de commission MG Hôte appliqué (%) | E3: 0.2
A4: Mois | B4: Nuits réservées | C4: Taux d'occupation | D4: CA (Recettes) | E4: Maintenance | F4: Consommables | G4: Électricité | H4: Eau | I4: Publicité | J4: Autres dépenses | K4: Total dépenses | L4: Résultat net | M4: Commission MG Hôte | N4: Montant dû propriétaire
A5: =EOMONTH(TODAY(),ROW()-17)+1 | B5: =SUMIFS(Réservations!$I$5:$I$204,Réservations!$G$5:$G$204,">="&$A5,Réservations!$G$5:$G$204,"<="&EOMONTH($A5,0),Réservations!$Q$5:$Q$204,"<>Annulée") | C5: =IFERROR($B5/(COUNTIFS(Biens!$H$5:$H$14,"Actif")*(EOMONTH($A5,0)-$A5+1)),0) | D5: =SUMIFS('Journal Financier'!$G$5:$G$304,'Journal Financier'!$A$5:$A$304,">="&$A5,'Journal Financier'!$A$5:$A$304,"<="&EOMONTH($A5,0),'Journal Financier'!$C$5:$C$304,"Recette") | E5: =SUMIFS('Journal Financier'!$F$5:$F$304,'Journal Financier'!$A$5:$A$304,">="&$A5,'Journal Financier'!$A$5:$A$304,"<="&EOMONTH($A5,0),'Journal Financier'!$C$5:$C$304,"Dépense",'Journal Financier'!$D$5:$D$304,"Maintenance") | F5: =SUMIFS('Journal Financier'!$F$5:$F$304,'Journal Financier'!$A$5:$A$304,">="&$A5,'Journal Financier'!$A$5:$A$304,"<="&EOMONTH($A5,0),'Journal Financier'!$C$5:$C$304,"Dépense",'Journal Financier'!$D$5:$D$304,"Consommables") | G5: =SUMIFS('Journal Financier'!$F$5:$F$304,'Journal Financier'!$A$5:$A$304,">="&$A5,'Journal Financier'!$A$5:$A$304,"<="&EOMONTH($A5,0),'Journal Financier'!$C$5:$C$304,"Dépense",'Journal Financier'!$D$5:$D$304,"Électricité") | H5: =SUMIFS('Journal Financier'!$F$5:$F$304,'Journal Financier'!$A$5:$A$304,">="&$A5,'Journal Financier'!$A$5:$A$304,"<="&EOMONTH($A5,0),'Journal Financier'!$C$5:$C$304,"Dépense",'Journal Financier'!$D$5:$D$304,"Eau") | I5: =SUMIFS('Journal Financier'!$F$5:$F$304,'Journal Financier'!$A$5:$A$304,">="&$A5,'Journal Financier'!$A$5:$A$304,"<="&EOMONTH($A5,0),'Journal Financier'!$C$5:$C$304,"Dépense",'Journal Financier'!$D$5:$D$304,"Publicité") | J5: =SUMIFS('Journal Financier'!$F$5:$F$304,'Journal Financier'!$A$5:$A$304,">="&$A5,'Journal Financier'!$A$5:$A$304,"<="&EOMONTH($A5,0),'Journal Financier'!$C$5:$C$304,"Dépense",'Journal Financier'!$D$5:$D$304,"Autre") | K5: =SUM(E5:J5) | L5: =D5-K5 | M5: =D5*$E$3 | N5: =L5-M5
A6: =EOMONTH(TODAY(),ROW()-17)+1 | B6: =SUMIFS(Réservations!$I$5:$I$204,Réservations!$G$5:$G$204,">="&$A6,Réservations!$G$5:$G$204,"<="&EOMONTH($A6,0),Réservations!$Q$5:$Q$204,"<>Annulée") | C6: =IFERROR($B6/(COUNTIFS(Biens!$H$5:$H$14,"Actif")*(EOMONTH($A6,0)-$A6+1)),0) | D6: =SUMIFS('Journal Financier'!$G$5:$G$304,'Journal Financier'!$A$5:$A$304,">="&$A6,'Journal Financier'!$A$5:$A$304,"<="&EOMONTH($A6,0),'Journal Financier'!$C$5:$C$304,"Recette") | E6: =SUMIFS('Journal Financier'!$F$5:$F$304,'Journal Financier'!$A$5:$A$304,">="&$A6,'Journal Financier'!$A$5:$A$304,"<="&EOMONTH($A6,0),'Journal Financier'!$C$5:$C$304,"Dépense",'Journal Financier'!$D$5:$D$304,"Maintenance") | F6: =SUMIFS('Journal Financier'!$F$5:$F$304,'Journal Financier'!$A$5:$A$304,">="&$A6,'Journal Financier'!$A$5:$A$304,"<="&EOMONTH($A6,0),'Journal Financier'!$C$5:$C$304,"Dépense",'Journal Financier'!$D$5:$D$304,"Consommables") | G6: =SUMIFS('Journal Financier'!$F$5:$F$304,'Journal Financier'!$A$5:$A$304,">="&$A6,'Journal Financier'!$A$5:$A$304,"<="&EOMONTH($A6,0),'Journal Financier'!$C$5:$C$304,"Dépense",'Journal Financier'!$D$5:$D$304,"Électricité") | H6: =SUMIFS('Journal Financier'!$F$5:$F$304,'Journal Financier'!$A$5:$A$304,">="&$A6,'Journal Financier'!$A$5:$A$304,"<="&EOMONTH($A6,0),'Journal Financier'!$C$5:$C$304,"Dépense",'Journal Financier'!$D$5:$D$304,"Eau") | I6: =SUMIFS('Journal Financier'!$F$5:$F$304,'Journal Financier'!$A$5:$A$304,">="&$A6,'Journal Financier'!$A$5:$A$304,"<="&EOMONTH($A6,0),'Journal Financier'!$C$5:$C$304,"Dépense",'Journal Financier'!$D$5:$D$304,"Publicité") | J6: =SUMIFS('Journal Financier'!$F$5:$F$304,'Journal Financier'!$A$5:$A$304,">="&$A6,'Journal Financier'!$A$5:$A$304,"<="&EOMONTH($A6,0),'Journal Financier'!$C$5:$C$304,"Dépense",'Journal Financier'!$D$5:$D$304,"Autre") | K6: =SUM(E6:J6) | L6: =D6-K6 | M6: =D6*$E$3 | N6: =L6-M6
A7: =EOMONTH(TODAY(),ROW()-17)+1 | B7: =SUMIFS(Réservations!$I$5:$I$204,Réservations!$G$5:$G$204,">="&$A7,Réservations!$G$5:$G$204,"<="&EOMONTH($A7,0),Réservations!$Q$5:$Q$204,"<>Annulée") | C7: =IFERROR($B7/(COUNTIFS(Biens!$H$5:$H$14,"Actif")*(EOMONTH($A7,0)-$A7+1)),0) | D7: =SUMIFS('Journal Financier'!$G$5:$G$304,'Journal Financier'!$A$5:$A$304,">="&$A7,'Journal Financier'!$A$5:$A$304,"<="&EOMONTH($A7,0),'Journal Financier'!$C$5:$C$304,"Recette") | E7: =SUMIFS('Journal Financier'!$F$5:$F$304,'Journal Financier'!$A$5:$A$304,">="&$A7,'Journal Financier'!$A$5:$A$304,"<="&EOMONTH($A7,0),'Journal Financier'!$C$5:$C$304,"Dépense",'Journal Financier'!$D$5:$D$304,"Maintenance") | F7: =SUMIFS('Journal Financier'!$F$5:$F$304,'Journal Financier'!$A$5:$A$304,">="&$A7,'Journal Financier'!$A$5:$A$304,"<="&EOMONTH($A7,0),'Journal Financier'!$C$5:$C$304,"Dépense",'Journal Financier'!$D$5:$D$304,"Consommables") | G7: =SUMIFS('Journal Financier'!$F$5:$F$304,'Journal Financier'!$A$5:$A$304,">="&$A7,'Journal Financier'!$A$5:$A$304,"<="&EOMONTH($A7,0),'Journal Financier'!$C$5:$C$304,"Dépense",'Journal Financier'!$D$5:$D$304,"Électricité") | H7: =SUMIFS('Journal Financier'!$F$5:$F$304,'Journal Financier'!$A$5:$A$304,">="&$A7,'Journal Financier'!$A$5:$A$304,"<="&EOMONTH($A7,0),'Journal Financier'!$C$5:$C$304,"Dépense",'Journal Financier'!$D$5:$D$304,"Eau") | I7: =SUMIFS('Journal Financier'!$F$5:$F$304,'Journal Financier'!$A$5:$A$304,">="&$A7,'Journal Financier'!$A$5:$A$304,"<="&EOMONTH($A7,0),'Journal Financier'!$C$5:$C$304,"Dépense",'Journal Financier'!$D$5:$D$304,"Publicité") | J7: =SUMIFS('Journal Financier'!$F$5:$F$304,'Journal Financier'!$A$5:$A$304,">="&$A7,'Journal Financier'!$A$5:$A$304,"<="&EOMONTH($A7,0),'Journal Financier'!$C$5:$C$304,"Dépense",'Journal Financier'!$D$5:$D$304,"Autre") | K7: =SUM(E7:J7) | L7: =D7-K7 | M7: =D7*$E$3 | N7: =L7-M7
A8: =EOMONTH(TODAY(),ROW()-17)+1 | B8: =SUMIFS(Réservations!$I$5:$I$204,Réservations!$G$5:$G$204,">="&$A8,Réservations!$G$5:$G$204,"<="&EOMONTH($A8,0),Réservations!$Q$5:$Q$204,"<>Annulée") | C8: =IFERROR($B8/(COUNTIFS(Biens!$H$5:$H$14,"Actif")*(EOMONTH($A8,0)-$A8+1)),0) | D8: =SUMIFS('Journal Financier'!$G$5:$G$304,'Journal Financier'!$A$5:$A$304,">="&$A8,'Journal Financier'!$A$5:$A$304,"<="&EOMONTH($A8,0),'Journal Financier'!$C$5:$C$304,"Recette") | E8: =SUMIFS('Journal Financier'!$F$5:$F$304,'Journal Financier'!$A$5:$A$304,">="&$A8,'Journal Financier'!$A$5:$A$304,"<="&EOMONTH($A8,0),'Journal Financier'!$C$5:$C$304,"Dépense",'Journal Financier'!$D$5:$D$304,"Maintenance") | F8: =SUMIFS('Journal Financier'!$F$5:$F$304,'Journal Financier'!$A$5:$A$304,">="&$A8,'Journal Financier'!$A$5:$A$304,"<="&EOMONTH($A8,0),'Journal Financier'!$C$5:$C$304,"Dépense",'Journal Financier'!$D$5:$D$304,"Consommables") | G8: =SUMIFS('Journal Financier'!$F$5:$F$304,'Journal Financier'!$A$5:$A$304,">="&$A8,'Journal Financier'!$A$5:$A$304,"<="&EOMONTH($A8,0),'Journal Financier'!$C$5:$C$304,"Dépense",'Journal Financier'!$D$5:$D$304,"Électricité") | H8: =SUMIFS('Journal Financier'!$F$5:$F$304,'Journal Financier'!$A$5:$A$304,">="&$A8,'Journal Financier'!$A$5:$A$304,"<="&EOMONTH($A8,0),'Journal Financier'!$C$5:$C$304,"Dépense",'Journal Financier'!$D$5:$D$304,"Eau") | I8: =SUMIFS('Journal Financier'!$F$5:$F$304,'Journal Financier'!$A$5:$A$304,">="&$A8,'Journal Financier'!$A$5:$A$304,"<="&EOMONTH($A8,0),'Journal Financier'!$C$5:$C$304,"Dépense",'Journal Financier'!$D$5:$D$304,"Publicité") | J8: =SUMIFS('Journal Financier'!$F$5:$F$304,'Journal Financier'!$A$5:$A$304,">="&$A8,'Journal Financier'!$A$5:$A$304,"<="&EOMONTH($A8,0),'Journal Financier'!$C$5:$C$304,"Dépense",'Journal Financier'!$D$5:$D$304,"Autre") | K8: =SUM(E8:J8) | L8: =D8-K8 | M8: =D8*$E$3 | N8: =L8-M8
A9: =EOMONTH(TODAY(),ROW()-17)+1 | B9: =SUMIFS(Réservations!$I$5:$I$204,Réservations!$G$5:$G$204,">="&$A9,Réservations!$G$5:$G$204,"<="&EOMONTH($A9,0),Réservations!$Q$5:$Q$204,"<>Annulée") | C9: =IFERROR($B9/(COUNTIFS(Biens!$H$5:$H$14,"Actif")*(EOMONTH($A9,0)-$A9+1)),0) | D9: =SUMIFS('Journal Financier'!$G$5:$G$304,'Journal Financier'!$A$5:$A$304,">="&$A9,'Journal Financier'!$A$5:$A$304,"<="&EOMONTH($A9,0),'Journal Financier'!$C$5:$C$304,"Recette") | E9: =SUMIFS('Journal Financier'!$F$5:$F$304,'Journal Financier'!$A$5:$A$304,">="&$A9,'Journal Financier'!$A$5:$A$304,"<="&EOMONTH($A9,0),'Journal Financier'!$C$5:$C$304,"Dépense",'Journal Financier'!$D$5:$D$304,"Maintenance") | F9: =SUMIFS('Journal Financier'!$F$5:$F$304,'Journal Financier'!$A$5:$A$304,">="&$A9,'Journal Financier'!$A$5:$A$304,"<="&EOMONTH($A9,0),'Journal Financier'!$C$5:$C$304,"Dépense",'Journal Financier'!$D$5:$D$304,"Consommables") | G9: =SUMIFS('Journal Financier'!$F$5:$F$304,'Journal Financier'!$A$5:$A$304,">="&$A9,'Journal Financier'!$A$5:$A$304,"<="&EOMONTH($A9,0),'Journal Financier'!$C$5:$C$304,"Dépense",'Journal Financier'!$D$5:$D$304,"Électricité") | H9: =SUMIFS('Journal Financier'!$F$5:$F$304,'Journal Financier'!$A$5:$A$304,">="&$A9,'Journal Financier'!$A$5:$A$304,"<="&EOMONTH($A9,0),'Journal Financier'!$C$5:$C$304,"Dépense",'Journal Financier'!$D$5:$D$304,"Eau") | I9: =SUMIFS('Journal Financier'!$F$5:$F$304,'Journal Financier'!$A$5:$A$304,">="&$A9,'Journal Financier'!$A$5:$A$304,"<="&EOMONTH($A9,0),'Journal Financier'!$C$5:$C$304,"Dépense",'Journal Financier'!$D$5:$D$304,"Publicité") | J9: =SUMIFS('Journal Financier'!$F$5:$F$304,'Journal Financier'!$A$5:$A$304,">="&$A9,'Journal Financier'!$A$5:$A$304,"<="&EOMONTH($A9,0),'Journal Financier'!$C$5:$C$304,"Dépense",'Journal Financier'!$D$5:$D$304,"Autre") | K9: =SUM(E9:J9) | L9: =D9-K9 | M9: =D9*$E$3 | N9: =L9-M9
A10: =EOMONTH(TODAY(),ROW()-17)+1 | B10: =SUMIFS(Réservations!$I$5:$I$204,Réservations!$G$5:$G$204,">="&$A10,Réservations!$G$5:$G$204,"<="&EOMONTH($A10,0),Réservations!$Q$5:$Q$204,"<>Annulée") | C10: =IFERROR($B10/(COUNTIFS(Biens!$H$5:$H$14,"Actif")*(EOMONTH($A10,0)-$A10+1)),0) | D10: =SUMIFS('Journal Financier'!$G$5:$G$304,'Journal Financier'!$A$5:$A$304,">="&$A10,'Journal Financier'!$A$5:$A$304,"<="&EOMONTH($A10,0),'Journal Financier'!$C$5:$C$304,"Recette") | E10: =SUMIFS('Journal Financier'!$F$5:$F$304,'Journal Financier'!$A$5:$A$304,">="&$A10,'Journal Financier'!$A$5:$A$304,"<="&EOMONTH($A10,0),'Journal Financier'!$C$5:$C$304,"Dépense",'Journal Financier'!$D$5:$D$304,"Maintenance") | F10: =SUMIFS('Journal Financier'!$F$5:$F$304,'Journal Financier'!$A$5:$A$304,">="&$A10,'Journal Financier'!$A$5:$A$304,"<="&EOMONTH($A10,0),'Journal Financier'!$C$5:$C$304,"Dépense",'Journal Financier'!$D$5:$D$304,"Consommables") | G10: =SUMIFS('Journal Financier'!$F$5:$F$304,'Journal Financier'!$A$5:$A$304,">="&$A10,'Journal Financier'!$A$5:$A$304,"<="&EOMONTH($A10,0),'Journal Financier'!$C$5:$C$304,"Dépense",'Journal Financier'!$D$5:$D$304,"Électricité") | H10: =SUMIFS('Journal Financier'!$F$5:$F$304,'Journal Financier'!$A$5:$A$304,">="&$A10,'Journal Financier'!$A$5:$A$304,"<="&EOMONTH($A10,0),'Journal Financier'!$C$5:$C$304,"Dépense",'Journal Financier'!$D$5:$D$304,"Eau") | I10: =SUMIFS('Journal Financier'!$F$5:$F$304,'Journal Financier'!$A$5:$A$304,">="&$A10,'Journal Financier'!$A$5:$A$304,"<="&EOMONTH($A10,0),'Journal Financier'!$C$5:$C$304,"Dépense",'Journal Financier'!$D$5:$D$304,"Publicité") | J10: =SUMIFS('Journal Financier'!$F$5:$F$304,'Journal Financier'!$A$5:$A$304,">="&$A10,'Journal Financier'!$A$5:$A$304,"<="&EOMONTH($A10,0),'Journal Financier'!$C$5:$C$304,"Dépense",'Journal Financier'!$D$5:$D$304,"Autre") | K10: =SUM(E10:J10) | L10: =D10-K10 | M10: =D10*$E$3 | N10: =L10-M10
A11: =EOMONTH(TODAY(),ROW()-17)+1 | B11: =SUMIFS(Réservations!$I$5:$I$204,Réservations!$G$5:$G$204,">="&$A11,Réservations!$G$5:$G$204,"<="&EOMONTH($A11,0),Réservations!$Q$5:$Q$204,"<>Annulée") | C11: =IFERROR($B11/(COUNTIFS(Biens!$H$5:$H$14,"Actif")*(EOMONTH($A11,0)-$A11+1)),0) | D11: =SUMIFS('Journal Financier'!$G$5:$G$304,'Journal Financier'!$A$5:$A$304,">="&$A11,'Journal Financier'!$A$5:$A$304,"<="&EOMONTH($A11,0),'Journal Financier'!$C$5:$C$304,"Recette") | E11: =SUMIFS('Journal Financier'!$F$5:$F$304,'Journal Financier'!$A$5:$A$304,">="&$A11,'Journal Financier'!$A$5:$A$304,"<="&EOMONTH($A11,0),'Journal Financier'!$C$5:$C$304,"Dépense",'Journal Financier'!$D$5:$D$304,"Maintenance") | F11: =SUMIFS('Journal Financier'!$F$5:$F$304,'Journal Financier'!$A$5:$A$304,">="&$A11,'Journal Financier'!$A$5:$A$304,"<="&EOMONTH($A11,0),'Journal Financier'!$C$5:$C$304,"Dépense",'Journal Financier'!$D$5:$D$304,"Consommables") | G11: =SUMIFS('Journal Financier'!$F$5:$F$304,'Journal Financier'!$A$5:$A$304,">="&$A11,'Journal Financier'!$A$5:$A$304,"<="&EOMONTH($A11,0),'Journal Financier'!$C$5:$C$304,"Dépense",'Journal Financier'!$D$5:$D$304,"Électricité") | H11: =SUMIFS('Journal Financier'!$F$5:$F$304,'Journal Financier'!$A$5:$A$304,">="&$A11,'Journal Financier'!$A$5:$A$304,"<="&EOMONTH($A11,0),'Journal Financier'!$C$5:$C$304,"Dépense",'Journal Financier'!$D$5:$D$304,"Eau") | I11: =SUMIFS('Journal Financier'!$F$5:$F$304,'Journal Financier'!$A$5:$A$304,">="&$A11,'Journal Financier'!$A$5:$A$304,"<="&EOMONTH($A11,0),'Journal Financier'!$C$5:$C$304,"Dépense",'Journal Financier'!$D$5:$D$304,"Publicité") | J11: =SUMIFS('Journal Financier'!$F$5:$F$304,'Journal Financier'!$A$5:$A$304,">="&$A11,'Journal Financier'!$A$5:$A$304,"<="&EOMONTH($A11,0),'Journal Financier'!$C$5:$C$304,"Dépense",'Journal Financier'!$D$5:$D$304,"Autre") | K11: =SUM(E11:J11) | L11: =D11-K11 | M11: =D11*$E$3 | N11: =L11-M11
A12: =EOMONTH(TODAY(),ROW()-17)+1 | B12: =SUMIFS(Réservations!$I$5:$I$204,Réservations!$G$5:$G$204,">="&$A12,Réservations!$G$5:$G$204,"<="&EOMONTH($A12,0),Réservations!$Q$5:$Q$204,"<>Annulée") | C12: =IFERROR($B12/(COUNTIFS(Biens!$H$5:$H$14,"Actif")*(EOMONTH($A12,0)-$A12+1)),0) | D12: =SUMIFS('Journal Financier'!$G$5:$G$304,'Journal Financier'!$A$5:$A$304,">="&$A12,'Journal Financier'!$A$5:$A$304,"<="&EOMONTH($A12,0),'Journal Financier'!$C$5:$C$304,"Recette") | E12: =SUMIFS('Journal Financier'!$F$5:$F$304,'Journal Financier'!$A$5:$A$304,">="&$A12,'Journal Financier'!$A$5:$A$304,"<="&EOMONTH($A12,0),'Journal Financier'!$C$5:$C$304,"Dépense",'Journal Financier'!$D$5:$D$304,"Maintenance") | F12: =SUMIFS('Journal Financier'!$F$5:$F$304,'Journal Financier'!$A$5:$A$304,">="&$A12,'Journal Financier'!$A$5:$A$304,"<="&EOMONTH($A12,0),'Journal Financier'!$C$5:$C$304,"Dépense",'Journal Financier'!$D$5:$D$304,"Consommables") | G12: =SUMIFS('Journal Financier'!$F$5:$F$304,'Journal Financier'!$A$5:$A$304,">="&$A12,'Journal Financier'!$A$5:$A$304,"<="&EOMONTH($A12,0),'Journal Financier'!$C$5:$C$304,"Dépense",'Journal Financier'!$D$5:$D$304,"Électricité") | H12: =SUMIFS('Journal Financier'!$F$5:$F$304,'Journal Financier'!$A$5:$A$304,">="&$A12,'Journal Financier'!$A$5:$A$304,"<="&EOMONTH($A12,0),'Journal Financier'!$C$5:$C$304,"Dépense",'Journal Financier'!$D$5:$D$304,"Eau") | I12: =SUMIFS('Journal Financier'!$F$5:$F$304,'Journal Financier'!$A$5:$A$304,">="&$A12,'Journal Financier'!$A$5:$A$304,"<="&EOMONTH($A12,0),'Journal Financier'!$C$5:$C$304,"Dépense",'Journal Financier'!$D$5:$D$304,"Publicité") | J12: =SUMIFS('Journal Financier'!$F$5:$F$304,'Journal Financier'!$A$5:$A$304,">="&$A12,'Journal Financier'!$A$5:$A$304,"<="&EOMONTH($A12,0),'Journal Financier'!$C$5:$C$304,"Dépense",'Journal Financier'!$D$5:$D$304,"Autre") | K12: =SUM(E12:J12) | L12: =D12-K12 | M12: =D12*$E$3 | N12: =L12-M12
A13: =EOMONTH(TODAY(),ROW()-17)+1 | B13: =SUMIFS(Réservations!$I$5:$I$204,Réservations!$G$5:$G$204,">="&$A13,Réservations!$G$5:$G$204,"<="&EOMONTH($A13,0),Réservations!$Q$5:$Q$204,"<>Annulée") | C13: =IFERROR($B13/(COUNTIFS(Biens!$H$5:$H$14,"Actif")*(EOMONTH($A13,0)-$A13+1)),0) | D13: =SUMIFS('Journal Financier'!$G$5:$G$304,'Journal Financier'!$A$5:$A$304,">="&$A13,'Journal Financier'!$A$5:$A$304,"<="&EOMONTH($A13,0),'Journal Financier'!$C$5:$C$304,"Recette") | E13: =SUMIFS('Journal Financier'!$F$5:$F$304,'Journal Financier'!$A$5:$A$304,">="&$A13,'Journal Financier'!$A$5:$A$304,"<="&EOMONTH($A13,0),'Journal Financier'!$C$5:$C$304,"Dépense",'Journal Financier'!$D$5:$D$304,"Maintenance") | F13: =SUMIFS('Journal Financier'!$F$5:$F$304,'Journal Financier'!$A$5:$A$304,">="&$A13,'Journal Financier'!$A$5:$A$304,"<="&EOMONTH($A13,0),'Journal Financier'!$C$5:$C$304,"Dépense",'Journal Financier'!$D$5:$D$304,"Consommables") | G13: =SUMIFS('Journal Financier'!$F$5:$F$304,'Journal Financier'!$A$5:$A$304,">="&$A13,'Journal Financier'!$A$5:$A$304,"<="&EOMONTH($A13,0),'Journal Financier'!$C$5:$C$304,"Dépense",'Journal Financier'!$D$5:$D$304,"Électricité") | H13: =SUMIFS('Journal Financier'!$F$5:$F$304,'Journal Financier'!$A$5:$A$304,">="&$A13,'Journal Financier'!$A$5:$A$304,"<="&EOMONTH($A13,0),'Journal Financier'!$C$5:$C$304,"Dépense",'Journal Financier'!$D$5:$D$304,"Eau") | I13: =SUMIFS('Journal Financier'!$F$5:$F$304,'Journal Financier'!$A$5:$A$304,">="&$A13,'Journal Financier'!$A$5:$A$304,"<="&EOMONTH($A13,0),'Journal Financier'!$C$5:$C$304,"Dépense",'Journal Financier'!$D$5:$D$304,"Publicité") | J13: =SUMIFS('Journal Financier'!$F$5:$F$304,'Journal Financier'!$A$5:$A$304,">="&$A13,'Journal Financier'!$A$5:$A$304,"<="&EOMONTH($A13,0),'Journal Financier'!$C$5:$C$304,"Dépense",'Journal Financier'!$D$5:$D$304,"Autre") | K13: =SUM(E13:J13) | L13: =D13-K13 | M13: =D13*$E$3 | N13: =L13-M13
A14: =EOMONTH(TODAY(),ROW()-17)+1 | B14: =SUMIFS(Réservations!$I$5:$I$204,Réservations!$G$5:$G$204,">="&$A14,Réservations!$G$5:$G$204,"<="&EOMONTH($A14,0),Réservations!$Q$5:$Q$204,"<>Annulée") | C14: =IFERROR($B14/(COUNTIFS(Biens!$H$5:$H$14,"Actif")*(EOMONTH($A14,0)-$A14+1)),0) | D14: =SUMIFS('Journal Financier'!$G$5:$G$304,'Journal Financier'!$A$5:$A$304,">="&$A14,'Journal Financier'!$A$5:$A$304,"<="&EOMONTH($A14,0),'Journal Financier'!$C$5:$C$304,"Recette") | E14: =SUMIFS('Journal Financier'!$F$5:$F$304,'Journal Financier'!$A$5:$A$304,">="&$A14,'Journal Financier'!$A$5:$A$304,"<="&EOMONTH($A14,0),'Journal Financier'!$C$5:$C$304,"Dépense",'Journal Financier'!$D$5:$D$304,"Maintenance") | F14: =SUMIFS('Journal Financier'!$F$5:$F$304,'Journal Financier'!$A$5:$A$304,">="&$A14,'Journal Financier'!$A$5:$A$304,"<="&EOMONTH($A14,0),'Journal Financier'!$C$5:$C$304,"Dépense",'Journal Financier'!$D$5:$D$304,"Consommables") | G14: =SUMIFS('Journal Financier'!$F$5:$F$304,'Journal Financier'!$A$5:$A$304,">="&$A14,'Journal Financier'!$A$5:$A$304,"<="&EOMONTH($A14,0),'Journal Financier'!$C$5:$C$304,"Dépense",'Journal Financier'!$D$5:$D$304,"Électricité") | H14: =SUMIFS('Journal Financier'!$F$5:$F$304,'Journal Financier'!$A$5:$A$304,">="&$A14,'Journal Financier'!$A$5:$A$304,"<="&EOMONTH($A14,0),'Journal Financier'!$C$5:$C$304,"Dépense",'Journal Financier'!$D$5:$D$304,"Eau") | I14: =SUMIFS('Journal Financier'!$F$5:$F$304,'Journal Financier'!$A$5:$A$304,">="&$A14,'Journal Financier'!$A$5:$A$304,"<="&EOMONTH($A14,0),'Journal Financier'!$C$5:$C$304,"Dépense",'Journal Financier'!$D$5:$D$304,"Publicité") | J14: =SUMIFS('Journal Financier'!$F$5:$F$304,'Journal Financier'!$A$5:$A$304,">="&$A14,'Journal Financier'!$A$5:$A$304,"<="&EOMONTH($A14,0),'Journal Financier'!$C$5:$C$304,"Dépense",'Journal Financier'!$D$5:$D$304,"Autre") | K14: =SUM(E14:J14) | L14: =D14-K14 | M14: =D14*$E$3 | N14: =L14-M14
A15: =EOMONTH(TODAY(),ROW()-17)+1 | B15: =SUMIFS(Réservations!$I$5:$I$204,Réservations!$G$5:$G$204,">="&$A15,Réservations!$G$5:$G$204,"<="&EOMONTH($A15,0),Réservations!$Q$5:$Q$204,"<>Annulée") | C15: =IFERROR($B15/(COUNTIFS(Biens!$H$5:$H$14,"Actif")*(EOMONTH($A15,0)-$A15+1)),0) | D15: =SUMIFS('Journal Financier'!$G$5:$G$304,'Journal Financier'!$A$5:$A$304,">="&$A15,'Journal Financier'!$A$5:$A$304,"<="&EOMONTH($A15,0),'Journal Financier'!$C$5:$C$304,"Recette") | E15: =SUMIFS('Journal Financier'!$F$5:$F$304,'Journal Financier'!$A$5:$A$304,">="&$A15,'Journal Financier'!$A$5:$A$304,"<="&EOMONTH($A15,0),'Journal Financier'!$C$5:$C$304,"Dépense",'Journal Financier'!$D$5:$D$304,"Maintenance") | F15: =SUMIFS('Journal Financier'!$F$5:$F$304,'Journal Financier'!$A$5:$A$304,">="&$A15,'Journal Financier'!$A$5:$A$304,"<="&EOMONTH($A15,0),'Journal Financier'!$C$5:$C$304,"Dépense",'Journal Financier'!$D$5:$D$304,"Consommables") | G15: =SUMIFS('Journal Financier'!$F$5:$F$304,'Journal Financier'!$A$5:$A$304,">="&$A15,'Journal Financier'!$A$5:$A$304,"<="&EOMONTH($A15,0),'Journal Financier'!$C$5:$C$304,"Dépense",'Journal Financier'!$D$5:$D$304,"Électricité") | H15: =SUMIFS('Journal Financier'!$F$5:$F$304,'Journal Financier'!$A$5:$A$304,">="&$A15,'Journal Financier'!$A$5:$A$304,"<="&EOMONTH($A15,0),'Journal Financier'!$C$5:$C$304,"Dépense",'Journal Financier'!$D$5:$D$304,"Eau") | I15: =SUMIFS('Journal Financier'!$F$5:$F$304,'Journal Financier'!$A$5:$A$304,">="&$A15,'Journal Financier'!$A$5:$A$304,"<="&EOMONTH($A15,0),'Journal Financier'!$C$5:$C$304,"Dépense",'Journal Financier'!$D$5:$D$304,"Publicité") | J15: =SUMIFS('Journal Financier'!$F$5:$F$304,'Journal Financier'!$A$5:$A$304,">="&$A15,'Journal Financier'!$A$5:$A$304,"<="&EOMONTH($A15,0),'Journal Financier'!$C$5:$C$304,"Dépense",'Journal Financier'!$D$5:$D$304,"Autre") | K15: =SUM(E15:J15) | L15: =D15-K15 | M15: =D15*$E$3 | N15: =L15-M15
A16: =EOMONTH(TODAY(),ROW()-17)+1 | B16: =SUMIFS(Réservations!$I$5:$I$204,Réservations!$G$5:$G$204,">="&$A16,Réservations!$G$5:$G$204,"<="&EOMONTH($A16,0),Réservations!$Q$5:$Q$204,"<>Annulée") | C16: =IFERROR($B16/(COUNTIFS(Biens!$H$5:$H$14,"Actif")*(EOMONTH($A16,0)-$A16+1)),0) | D16: =SUMIFS('Journal Financier'!$G$5:$G$304,'Journal Financier'!$A$5:$A$304,">="&$A16,'Journal Financier'!$A$5:$A$304,"<="&EOMONTH($A16,0),'Journal Financier'!$C$5:$C$304,"Recette") | E16: =SUMIFS('Journal Financier'!$F$5:$F$304,'Journal Financier'!$A$5:$A$304,">="&$A16,'Journal Financier'!$A$5:$A$304,"<="&EOMONTH($A16,0),'Journal Financier'!$C$5:$C$304,"Dépense",'Journal Financier'!$D$5:$D$304,"Maintenance") | F16: =SUMIFS('Journal Financier'!$F$5:$F$304,'Journal Financier'!$A$5:$A$304,">="&$A16,'Journal Financier'!$A$5:$A$304,"<="&EOMONTH($A16,0),'Journal Financier'!$C$5:$C$304,"Dépense",'Journal Financier'!$D$5:$D$304,"Consommables") | G16: =SUMIFS('Journal Financier'!$F$5:$F$304,'Journal Financier'!$A$5:$A$304,">="&$A16,'Journal Financier'!$A$5:$A$304,"<="&EOMONTH($A16,0),'Journal Financier'!$C$5:$C$304,"Dépense",'Journal Financier'!$D$5:$D$304,"Électricité") | H16: =SUMIFS('Journal Financier'!$F$5:$F$304,'Journal Financier'!$A$5:$A$304,">="&$A16,'Journal Financier'!$A$5:$A$304,"<="&EOMONTH($A16,0),'Journal Financier'!$C$5:$C$304,"Dépense",'Journal Financier'!$D$5:$D$304,"Eau") | I16: =SUMIFS('Journal Financier'!$F$5:$F$304,'Journal Financier'!$A$5:$A$304,">="&$A16,'Journal Financier'!$A$5:$A$304,"<="&EOMONTH($A16,0),'Journal Financier'!$C$5:$C$304,"Dépense",'Journal Financier'!$D$5:$D$304,"Publicité") | J16: =SUMIFS('Journal Financier'!$F$5:$F$304,'Journal Financier'!$A$5:$A$304,">="&$A16,'Journal Financier'!$A$5:$A$304,"<="&EOMONTH($A16,0),'Journal Financier'!$C$5:$C$304,"Dépense",'Journal Financier'!$D$5:$D$304,"Autre") | K16: =SUM(E16:J16) | L16: =D16-K16 | M16: =D16*$E$3 | N16: =L16-M16

Sheet Ménage
A1: MG HÔTE | C1: SUIVI MÉNAGE
C2: Statut, prestataire et compte rendu par passage
A4: Date | B4: Bien | C4: Réservation liée | D4: Statut | E4: Prestataire | F4: Heure prévue | G4: Heure réalisée | H4: Compte rendu ménage | I4: Anomalies / dégâts constatés | J4: Consommables à racheter | K4: Notes

Sheet Maintenance
A1: MG HÔTE | C1: SUIVI MAINTENANCE
C2: Incidents, priorité et résolution
A4: Date signalement | B4: Bien | C4: Incident | D4: Priorité | E4: Statut | F4: Responsable | G4: Date résolution prévue | H4: Date résolution réelle | I4: Coût (MAD) | J4: Notes

Sheet Facture Propriétaire
A1: MG HÔTE | C1: FACTURE PROPRIÉTAIRE
C2: Fiche propriétaire + décompte financier de la période — prêt à exporter en PDF
A4: N° Facture | C4: FACT-2026-001 | E4: Date d'émission | G4: =TODAY()
A5: Propriétaire | E5: Bien concerné
A6: Période — du | E6: au
A8: COORDONNÉES PROPRIÉTAIRE (automatique)
A9: Téléphone | C9: =IFERROR(INDEX(Propriétaires!$C$5:$C$14,MATCH($C$5,Propriétaires!$A$5:$A$14,0)),"") | E9: Email | G9: =IFERROR(INDEX(Propriétaires!$D$5:$D$14,MATCH($C$5,Propriétaires!$A$5:$A$14,0)),"")
A10: Adresse | C10: =IFERROR(INDEX(Propriétaires!$E$5:$E$14,MATCH($C$5,Propriétaires!$A$5:$A$14,0)),"") | E10: RIB / IBAN | G10: =IFERROR(INDEX(Propriétaires!$F$5:$F$14,MATCH($C$5,Propriétaires!$A$5:$A$14,0)),"")
A13: DÉTAIL FINANCIER DE LA PÉRIODE
A14: Élément | G14: Montant
A15: Chiffre d'affaires brut des réservations (Prix total) | G15: =SUMIFS(Réservations!$L$5:$L$204,Réservations!$B$5:$B$204,$G$5,Réservations!$G$5:$G$204,">="&$C$6,Réservations!$G$5:$G$204,"<="&$G$6,Réservations!$Q$5:$Q$204,"<>Annulée")
A16: Frais plateforme (Airbnb / Booking) | G16: =SUMIFS(Réservations!$M$5:$M$204,Réservations!$B$5:$B$204,$G$5,Réservations!$G$5:$G$204,">="&$C$6,Réservations!$G$5:$G$204,"<="&$G$6,Réservations!$Q$5:$Q$204,"<>Annulée")
A17: Montant net après frais plateforme | G17: =SUMIFS(Réservations!$N$5:$N$204,Réservations!$B$5:$B$204,$G$5,Réservations!$G$5:$G$204,">="&$C$6,Réservations!$G$5:$G$204,"<="&$G$6,Réservations!$Q$5:$Q$204,"<>Annulée")
A18: Taux de commission MG Hôte | G18: =IFERROR(INDEX(Biens!$I$5:$I$14,MATCH($G$5,Biens!$A$5:$A$14,0)),0)
A19: Montant commission MG Hôte | G19: =SUMIFS(Réservations!$O$5:$O$204,Réservations!$B$5:$B$204,$G$5,Réservations!$G$5:$G$204,">="&$C$6,Réservations!$G$5:$G$204,"<="&$G$6,Réservations!$Q$5:$Q$204,"<>Annulée")
A20: Charges refacturées au propriétaire : | G20: =""
A21: Maintenance | G21: =SUMIFS('Journal Financier'!$F$5:$F$304,'Journal Financier'!$B$5:$B$304,$G$5,'Journal Financier'!$C$5:$C$304,"Dépense",'Journal Financier'!$D$5:$D$304,"Maintenance",'Journal Financier'!$A$5:$A$304,">="&$C$6,'Journal Financier'!$A$5:$A$304,"<="&$G$6)
A22: Consommables | G22: =SUMIFS('Journal Financier'!$F$5:$F$304,'Journal Financier'!$B$5:$B$304,$G$5,'Journal Financier'!$C$5:$C$304,"Dépense",'Journal Financier'!$D$5:$D$304,"Consommables",'Journal Financier'!$A$5:$A$304,">="&$C$6,'Journal Financier'!$A$5:$A$304,"<="&$G$6)
A23: Électricité | G23: =SUMIFS('Journal Financier'!$F$5:$F$304,'Journal Financier'!$B$5:$B$304,$G$5,'Journal Financier'!$C$5:$C$304,"Dépense",'Journal Financier'!$D$5:$D$304,"Électricité",'Journal Financier'!$A$5:$A$304,">="&$C$6,'Journal Financier'!$A$5:$A$304,"<="&$G$6)
A24: Eau | G24: =SUMIFS('Journal Financier'!$F$5:$F$304,'Journal Financier'!$B$5:$B$304,$G$5,'Journal Financier'!$C$5:$C$304,"Dépense",'Journal Financier'!$D$5:$D$304,"Eau",'Journal Financier'!$A$5:$A$304,">="&$C$6,'Journal Financier'!$A$5:$A$304,"<="&$G$6)
A25: Publicité | G25: =SUMIFS('Journal Financier'!$F$5:$F$304,'Journal Financier'!$B$5:$B$304,$G$5,'Journal Financier'!$C$5:$C$304,"Dépense",'Journal Financier'!$D$5:$D$304,"Publicité",'Journal Financier'!$A$5:$A$304,">="&$C$6,'Journal Financier'!$A$5:$A$304,"<="&$G$6)
A26: Sous-total charges refacturées | G26: =SUM(G21:G25)
A27: MONTANT NET À VERSER AU PROPRIÉTAIRE | G27: =G17-G19-G26
A30: Fait à ______________________, le | D30: =TODAY()
A33: Signature MG Hôte | E33: Signature Propriétaire

Sheet Rapport Mensuel
A1: MG HÔTE | C1: RAPPORT MENSUEL D'ACTIVITÉ
C2: Synthèse complète du mois sélectionné — prêt à exporter en PDF
A4: Mois analysé (1er jour du mois) | D4: =EOMONTH(TODAY(),-1)+1 | E4: Commission (%) | F4: 0.2
A6: INDICATEURS DU MOIS
A7: Nuits réservées | E7: =SUMIFS(Réservations!$I$5:$I$204,Réservations!$G$5:$G$204,">="&$D$4,Réservations!$G$5:$G$204,"<="&EOMONTH($D$4,0),Réservations!$Q$5:$Q$204,"<>Annulée")
A8: Taux d'occupation | E8: =IFERROR(E7/(COUNTIFS(Biens!$H$5:$H$14,"Actif")*(EOMONTH($D$4,0)-$D$4+1)),0)
A9: Nombre de réservations confirmées | E9: =COUNTIFS(Réservations!$G$5:$G$204,">="&$D$4,Réservations!$G$5:$G$204,"<="&EOMONTH($D$4,0),Réservations!$Q$5:$Q$204,"Confirmée")
A10: Chiffre d'affaires (CA) du mois | E10: =SUMIFS('Journal Financier'!$G$5:$G$304,'Journal Financier'!$A$5:$A$304,">="&$D$4,'Journal Financier'!$A$5:$A$304,"<="&EOMONTH($D$4,0),'Journal Financier'!$C$5:$C$304,"Recette")
A12: DÉPENSES DÉTAILLÉES PAR CATÉGORIE
A13: Maintenance | E13: =SUMIFS('Journal Financier'!$F$5:$F$304,'Journal Financier'!$A$5:$A$304,">="&$D$4,'Journal Financier'!$A$5:$A$304,"<="&EOMONTH($D$4,0),'Journal Financier'!$C$5:$C$304,"Dépense",'Journal Financier'!$D$5:$D$304,"Maintenance")
A14: Consommables | E14: =SUMIFS('Journal Financier'!$F$5:$F$304,'Journal Financier'!$A$5:$A$304,">="&$D$4,'Journal Financier'!$A$5:$A$304,"<="&EOMONTH($D$4,0),'Journal Financier'!$C$5:$C$304,"Dépense",'Journal Financier'!$D$5:$D$304,"Consommables")
A15: Électricité | E15: =SUMIFS('Journal Financier'!$F$5:$F$304,'Journal Financier'!$A$5:$A$304,">="&$D$4,'Journal Financier'!$A$5:$A$304,"<="&EOMONTH($D$4,0),'Journal Financier'!$C$5:$C$304,"Dépense",'Journal Financier'!$D$5:$D$304,"Électricité")
A16: Eau | E16: =SUMIFS('Journal Financier'!$F$5:$F$304,'Journal Financier'!$A$5:$A$304,">="&$D$4,'Journal Financier'!$A$5:$A$304,"<="&EOMONTH($D$4,0),'Journal Financier'!$C$5:$C$304,"Dépense",'Journal Financier'!$D$5:$D$304,"Eau")
A17: Publicité | E17: =SUMIFS('Journal Financier'!$F$5:$F$304,'Journal Financier'!$A$5:$A$304,">="&$D$4,'Journal Financier'!$A$5:$A$304,"<="&EOMONTH($D$4,0),'Journal Financier'!$C$5:$C$304,"Dépense",'Journal Financier'!$D$5:$D$304,"Publicité")
A18: Autres dépenses | E18: =SUMIFS('Journal Financier'!$F$5:$F$304,'Journal Financier'!$A$5:$A$304,">="&$D$4,'Journal Financier'!$A$5:$A$304,"<="&EOMONTH($D$4,0),'Journal Financier'!$C$5:$C$304,"Dépense",'Journal Financier'!$D$5:$D$304,"Autre")
A19: Total dépenses du mois | E19: =SUM(E13:E18)
A20: Résultat net du mois | E20: =E10-E19
A21: Commission MG Hôte | E21: =E10*$F$4
A22: MONTANT DÛ AU PROPRIÉTAIRE | E22: =E20-E21
A24: ALERTES DU MOIS
A25: Ménages en attente sur ce mois | E25: =COUNTIFS('Ménage'!$A$5:$A$154,">="&$D$4,'Ménage'!$A$5:$A$154,"<="&EOMONTH($D$4,0),'Ménage'!$D$5:$D$154,"En attente")
A26: Incidents maintenance non résolus signalés ce mois | E26: =COUNTIFS(Maintenance!$A$5:$A$104,">="&$D$4,Maintenance!$A$5:$A$104,"<="&EOMONTH($D$4,0),Maintenance!$E$5:$E$104,"<>Résolu")
A27: Voyageurs non payés (séjour déjà terminé, toutes réservations) | E27: =COUNTIFS(Réservations!$R$5:$R$204,"Non payé",Réservations!$H$5:$H$204,"<"&TODAY())
A29: ="Rapport généré le "&TEXT(TODAY(),"dd/mm/yyyy")&" — MG Hôte, conciergerie Airbnb & Booking"

Sheet Paramètres
A1: PARAMÈTRES — Listes de référence (ne pas supprimer, utilisées par les listes déroulantes)
B2: Biens | C2: Biens + Général | D2: Plateformes | E2: Statuts réservation | F2: Types de bien | G2: Statuts bien | H2: Statuts ménage | I2: Priorités maintenance | J2: Statuts maintenance | K2: Types journal | L2: Catégories journal | M2: Modes de paiement | N2: Statuts paiement voyageur
B3: =IF(Biens!A5="","",Biens!A5) | C3: =IF(Biens!A5="","",Biens!A5) | D3: Airbnb | E3: Confirmée | F3: Villa | G3: Actif | H3: Fait | I3: Urgente | J3: Ouvert | K3: Recette | L3: Loyer Airbnb | M3: Virement | N3: Payé
B4: =IF(Biens!A6="","",Biens!A6) | C4: =IF(Biens!A6="","",Biens!A6) | D4: Booking | E4: En attente | F4: Appartement | G4: Inactif | H4: En attente | I4: Haute | J4: En cours | K4: Dépense | L4: Loyer Booking | M4: Espèces | N4: Partiel
B5: =IF(Biens!A7="","",Biens!A7) | C5: =IF(Biens!A7="","",Biens!A7) | D5: Direct | E5: Terminée | F5: Riad | I5: Normale | J5: Résolu | L5: Loyer Direct | M5: Chèque | N5: Non payé
B6: =IF(Biens!A8="","",Biens!A8) | C6: =IF(Biens!A8="","",Biens!A8) | E6: Annulée | I6: Basse | L6: Commission MG Hôte | M6: Carte bancaire
B7: =IF(Biens!A9="","",Biens!A9) | C7: =IF(Biens!A9="","",Biens!A9) | L7: Maintenance | M7: Autre
B8: =IF(Biens!A10="","",Biens!A10) | C8: =IF(Biens!A10="","",Biens!A10) | L8: Consommables
B9: =IF(Biens!A11="","",Biens!A11) | C9: =IF(Biens!A11="","",Biens!A11) | L9: Électricité
B10: =IF(Biens!A12="","",Biens!A12) | C10: =IF(Biens!A12="","",Biens!A12) | L10: Eau
B11: =IF(Biens!A13="","",Biens!A13) | C11: =IF(Biens!A13="","",Biens!A13) | L11: Publicité
B12: =IF(Biens!A14="","",Biens!A14) | C12: =IF(Biens!A14="","",Biens!A14) | L12: Reversement propriétaire
C13: Général (MG Hôte) | L13: Autre
